Workbook
Name allowed117_fp_S_class_3757: 'Valid Values'!$AU$2:$AU$3
Name allowed117_fp_S_class_6161: 'Valid Values'!$AU$2:$AU$3
Name allowed1217_fp_S_class_3757: 'Valid Values'!$E$2:$E$11
Name allowed1316_fp_S_class_3757: 'Valid Values'!$AC$2:$AC$21
Name allowed1316_fp_S_class_6161: 'Valid Values'!$AC$2:$AC$21
Name allowed135_fp_S_class_3757: 'Valid Values'!$AO$2:$AO$26
Name allowed135_fp_S_class_6161: 'Valid Values'!$AO$2:$AO$26
Name allowed1379_fp_S_class_3757: 'Valid Values'!$W$2:$W$8
Name allowed137_fp_S_class_3757: 'Valid Values'!$Q$2:$Q$27
Name allowed1386_fp_S_class_6161: 'Valid Values'!$CB$2:$CB$564
Name allowed1388_fp_S_class_3757: 'Valid Values'!$AG$2:$AG$179
Name allowed1388_fp_S_class_6161: 'Valid Values'!$AG$2:$AG$179
Name allowed1436_fp_S_class_6161: 'Valid Values'!$CP$2:$CP$31
Name allowed1437_fp_S_class_3757: 'Valid Values'!$Y$2:$Y$20
Name allowed1437_fp_S_class_6161: 'Valid Values'!$CL$2:$CL$12
Name allowed1557_fp_S_class_3757: 'Valid Values'!$AK$2:$AK$15
Name allowed1557_fp_S_class_6161: 'Valid Values'!$AK$2:$AK$15
Name allowed1560_fp_S_class_3757: 'Valid Values'!$M$2:$M$30
Name allowed1567_fp_S_class_3757: 'Valid Values'!$AA$2:$AA$15
Name allowed1966_fp_S_class_3757: 'Valid Values'!$C$2:$C$33
Name allowed2358_fp_S_class_6161: 'Valid Values'!$CJ$2:$CJ$312
Name allowed2385_fp_S_class_3757: 'Valid Values'!$G$2:$G$44
Name allowed2385_fp_S_class_6161: 'Valid Values'!$BV$2:$BV$17
Name allowed2389_fp_S_class_3757: 'Valid Values'!$K$2:$K$5
Name allowed256_fp_S_class_3757: 'Valid Values'!$AQ$2:$AQ$3
Name allowed256_fp_S_class_6161: 'Valid Values'!$AQ$2:$AQ$3
Name allowed27_fp_S_class_6161: 'Valid Values'!$CN$2:$CN$3
Name allowed28_fp_S_class_3757: 'Valid Values'!$AM$2:$AM$4
Name allowed28_fp_S_class_6161: 'Valid Values'!$AM$2:$AM$4
Name allowed31_fp_S_class_3757: 'Valid Values'!$AS$2:$AS$3
Name allowed31_fp_S_class_6161: 'Valid Values'!$AS$2:$AS$3
Name allowed3538_fp_S_class_3757: 'Valid Values'!$I$2:$I$27
Name allowed3921_fp_S_class_6161: 'Valid Values'!$CH$2:$CH$7
Name allowed4123_fp_S_class_6161: 'Valid Values'!$BX$2:$BX$11
Name allowed4591_fp_S_class_6161: 'Valid Values'!$CF$2:$CF$6
Name allowed5471_fp_S_class_6161: 'Valid Values'!$BT$2:$BT$6
Name allowed6012_fp_S_class_6161: 'Valid Values'!$BR$2:$BR$6
Name allowed6109_fp_S_class_3757: 'Valid Values'!$A$2:$A$14
Name allowed6109_fp_S_class_6161: 'Valid Values'!$BP$2:$BP$9
Name allowed6253_fp_S_class_3757: 'Valid Values'!$AE$2:$AE$5
Name allowed647_fp_S_class_3757: 'Valid Values'!$O$2:$O$248
Name allowed647_fp_S_class_6161: 'Valid Values'!$O$2:$O$248
Name allowed807_fp_S_class_3757: 'Valid Values'!$U$2:$U$5
Name allowed807_fp_S_class_6161: 'Valid Values'!$U$2:$U$5
Name allowed8205_fp_S_class_3757: 'Valid Values'!$AW$2:$AW$4
Name allowed82_fp_S_class_6161: 'Valid Values'!$CD$2:$CD$40
Name allowed8462_fp_S_class_3757: 'Valid Values'!$AY$2:$AY$4
Name allowed8462_fp_S_class_6161: 'Valid Values'!$AY$2:$AY$4
Name allowed8653_fp_S_class_3757: 'Valid Values'!$AI$2:$AI$10
Name allowed8653_fp_S_class_6161: 'Valid Values'!$BZ$2:$BZ$4
Name allowed9007_fp_S_class_3757: 'Valid Values'!$BA$2:$BA$2
Name allowed9007_fp_S_class_6161: 'Valid Values'!$BA$2:$BA$2
Name allowed9009_fp_S_class_3757: 'Valid Values'!$BB$2:$BB$4
Name allowed9009_fp_S_class_6161: 'Valid Values'!$BB$2:$BB$4
Name allowed9011_fp_S_class_3757: 'Valid Values'!$BC$2:$BC$3
Name allowed9011_fp_S_class_6161: 'Valid Values'!$CR$2:$CR$4
Name allowed9030_fp_S_class_3757: 'Valid Values'!$BD$2:$BD$3
Name allowed9030_fp_S_class_6161: 'Valid Values'!$BD$2:$BD$3
Name allowed9031_fp_S_class_3757: 'Valid Values'!$BE$2:$BE$19
Name allowed9031_fp_S_class_6161: 'Valid Values'!$BE$2:$BE$19

Sheet Instructions
A1: New Features | D1: For Mandarin translations of product questions, please click here. All answer inputs should still be provided in English. 点击此处查看所有产品相关问题的中文翻译。
A2: Variant Grouping
A3: If you have indicated that you will provide variant grouping data via template settings, additional columns for variant grouping information have been added to the class | C3: Legends
A4: sheet. Enter a common identifier to indicate which part numbers should be grouped together, select attribute(s) to group variants by (or enter custom category if | C4: Cell Fill Colors
A5: desired category is not included in the dropdown), and provide corresponding variant attribute. Groupings that violate Wayfair's Do Not Join rules will be excluded. | C5: Light Red | D5: Missing required data
A6: If Wayfair detects additional variants, products will be grouped further after submission. | C6: Gray | D6: Not required/will be autofilled*
C7: Red | D7: Error/incorrect answer
A8: Class Sheet Instructions | C8: Blue | D8: Autofill suggested by Wayfair (review needed)
A9: All data provided in the class sheet feeds directly to the customer-facing Product Details Page (PDP), optimizes search and enables order fulfillment. Please ensure the | C9: Yellow | D9: Warning
A10: data provided is accurate and as detailed as possible. | C10: No fill | D10: Validated/no action required
D11: * For products that have already been submitted, the entire row will be filled gray and cannot be edited further
A12: Conditional Formatting
A13: Some answers to questions on the spec sheet are dependent on upstream responses, whether they are related to attributes like material type, existence of features | C13: Data Priority
A14: or compliance. Real-time cell coloring per the legend indicates whether an input is required, has an error or has a conditional rule applied. | C14: Required | D14: Data required for product to be live on site
C15: Recommended | D15: Not required but recommended to improve search and browse
A16: Error Guidance | C16: Additional | D16: Optional but enhances listings for customers
A17: Errors are highlighted on the Error Summary Tab which shows a summary of all errors across all sheets with high level details and hyperlinks to the corresponding | C17: Conditional | D17: Data may be required based on prior responses
A18: cell where the error occurred. Additionally, a new Error Status Column at the beginning of each class sheet will show the status of each row and will display the first error
A19: error message in that row, and will update as errors are resolved from left to right. | C19: Data Type
C20: Text | D20: Enter a text-based response
A21: Notes: | C21: Single-Select | D21: Select one option from a list of provided options (listed in a dropdown on the cell)
A22: • Column headers provide additional information on the data required for each column. | C22: Multi-Select | D22: Enter one or more options from a list of provided options, separated using a semi-colon (;)
A23: • Completing Recommended and Additional fields further enhances the customer experience and improves the quality of listings for better product discovery. | C23: Number* | D23: Enter a decimal numeric response with up to 2 decimal points
A24: • Marketing Copy should provide a compelling, informative overview of the product, ensuring it effectively highlights key features, benefits, and use cases. | C24: Whole Number* | D24: Enter an integer (whole number) numeric response
A25: Incorporating comprehensive, descriptive language will enable future enhancements for capturing and improving product tagging. | C25: Yes or No | D25: Enter a Yes, No or Does Not Apply response (listed in a dropdown on the cell)
A26: ◦ Provide key selling point(s)/feature(s) that differentiate your product and inform customers about your product and encourage purchase. | D26: * Does Not Apply is a valid response when applicable
A27: ◦ Either Marketing Copy OR at least 3 Feature Bullets are required. Feature bullets will be displayed on Wayfair PDP in bulleted form.
A28: • The order in which media is input may not be reflected in order of imagery on the product page.
A29: • A maximum of 3 videos can be displayed in the product media tray on the product detail page. Additional videos may be showcased through Waymore content.
A30: • If all products in a class have the same answer to a question, a default value can be set. An answer entered in the Default Answer row will be applied to all products
A31: in that class automatically. Additional products added to this class in the future will have the same default value applied as well. For any products that have a
A32: different answer than others in the class, enter the answer manually to the applicable row to bypass the default just for that question and product.
A33: • Expandable columns can be used to add additional information directly within the main spec sheet as needed for supported sections by clicking the "+" sign
A34: above the section.
A36: Instructions for Repeatable Questions
A37: Some questions can be answered multiple times based on your product set up. For example, you can add anywhere between 1 and 30 images per product.
A38: For these questions, look for the "plus" button above that section and click it to expand to more columns. You can do this multiple times until you reach the max.
A39: Depends on the type of product you are adding, some of these questions may not be shown or required.
... A66: The Failed Products tab will only appear if products in your submission fail to upload. Failed products must be added to a new template and re-uploaded before resubmission.

Sheet Error Summary
A1: This Error Summary tab lists all errors and warnings in the spec sheet. Each entry includes a link to the specific cell and detailed information about the issue.
A2: Status | B2: Location | C2: Sheet Name | D2: Supplier Part Number | E2: Field | F2: Provided Answer | G2: Error Message
A3: {=_xlfn.LET(_xlpm.cf3757_STANDARDData, GetSheetStatusData(ClassFeed3757_STANDARDTracker, ClassFeed3757_STANDARDErrors), _xlpm.cf6161_STANDARDData, GetSheetStatusData(ClassFeed6161_STANDARDTracker, ClassFeed6161_STANDARDErrors), _xlpm.stackedData, _xlfn.VSTACK(_xlpm.cf3757_STANDARDData, _xlpm.cf6161_STANDARDData), _xlfn._xlws.FILTER(_xlpm.stackedData, _xlpm.stackedData<>"", ""))} -> 0 | B3: =IF(AND(C3<>"", H3<>""), HYPERLINK("#'" & C3 & "'!" & H3, H3), "") -> 0 | C3: {=_xlfn.LET(_xlpm.cf3757_STANDARDData, GetSheetNameData(ClassFeed3757_STANDARDTracker, ClassFeed3757_STANDARDErrors, "3757 - Wall Stickers (S)"), _xlpm.cf6161_STANDARDData, GetSheetNameData(ClassFeed6161_STANDARDTracker, ClassFeed6161_STANDARDErrors, "6161 - Wallpaper (S)"), _xlpm.stackedData, _xlfn.VSTACK(_xlpm.cf3757_STANDARDData, _xlpm.cf6161_STANDARDData), _xlfn._xlws.FILTER(_xlpm.stackedData, _xlpm.stackedData<>"", ""))} -> 0 | D3: {=_xlfn.LET(_xlpm.cf3757_STANDARDPartNumbers, GetSheetSupplierPartNumbers(ClassFeed3757_STANDARDTracker, ClassFeed3757_STANDARDErrors, '3757 - Wall Stickers (S)'!$B:$B), _xlpm.cf6161_STANDARDPartNumbers, GetSheetSupplierPartNumbers(ClassFeed6161_STANDARDTracker, ClassFeed6161_STANDARDErrors, '6161 - Wallpaper (S)'!$B:$B), _xlpm.stackedPartNumbers, _xlfn.VSTACK(_xlpm.cf3757_STANDARDPartNumbers, _xlpm.cf6161_STANDARDPartNumbers), _xlfn._xlws.FILTER(_xlpm.stackedPartNumbers, _xlpm.stackedPartNumbers<>"", ""))} -> 0 | E3: {=_xlfn.LET(_xlpm.cf3757_STANDARDQuestionDisplayNames, GetErrorQuestionDisplayNames(ClassFeed3757_STANDARDHeaders, ClassFeed3757_STANDARDTracker, ClassFeed3757_STANDARDErrors), _xlpm.cf6161_STANDARDQuestionDisplayNames, GetErrorQuestionDisplayNames(ClassFeed6161_STANDARDHeaders, ClassFeed6161_STANDARDTracker, ClassFeed6161_STANDARDErrors), _xlpm.stackedQuestionDisplayNames, _xlfn.VSTACK(_xlpm.cf3757_STANDARDQuestionDisplayNames, _xlpm.cf6161_STANDARDQuestionDisplayNames), _xlfn._xlws.FILTER(_xlpm.stackedQuestionDisplayNames, _xlpm.stackedQuestionDisplayNames<>"", ""))} -> 0 | F3: {=_xlfn.LET(_xlpm.cf3757_STANDARDProvidedAnswers, GetFilteredProvidedAnswers(ClassFeed3757_STANDARDAnswers, ClassFeed3757_STANDARDErrors, ClassFeed3757_STANDARDTracker), _xlpm.cf6161_STANDARDProvidedAnswers, GetFilteredProvidedAnswers(ClassFeed6161_STANDARDAnswers, ClassFeed6161_STANDARDErrors, ClassFeed6161_STANDARDTracker), _xlpm.stackedProvidedAnswers, _xlfn.VSTACK(_xlpm.cf3757_STANDARDProvidedAnswers, _xlpm.cf6161_STANDARDProvidedAnswers), _xlfn._xlws.FILTER(_xlpm.stackedProvidedAnswers, _xlpm.stackedProvidedAnswers<>"EMPTY_ERROR", ""))} -> 0 | G3: {=_xlfn.LET(_xlpm.cf3757_STANDARDErrorMessages, _xlfn.FILTER(_xlfn.TOCOL(ClassFeed3757_STANDARDErrors), _xlfn.TOCOL((ClassFeed3757_STANDARDErrors <> "") * (ClassFeed3757_STANDARDTracker <> "Valid") * (ClassFeed3757_STANDARDTracker <> "Disabled")), ""), _xlpm.cf6161_STANDARDErrorMessages, _xlfn.FILTER(_xlfn.TOCOL(ClassFeed6161_STANDARDErrors), _xlfn.TOCOL((ClassFeed6161_STANDARDErrors <> "") * (ClassFeed6161_STANDARDTracker <> "Valid") * (ClassFeed6161_STANDARDTracker <> "Disabled")), ""), _xlpm.stackedErrorMessages, _xlfn.VSTACK(_xlpm.cf3757_STANDARDErrorMessages, _xlpm.cf6161_STANDARDErrorMessages), _xlpm.filteredMessages, _xlfn._xlws.FILTER(_xlpm.stackedErrorMessages, _xlpm.stackedErrorMessages<>"", ""), IFERROR(_xlfn.TEXTAFTER(_xlpm.filteredMessages, ":"), _xlpm.filteredMessages))} -> 0 | H3: {=_xlfn.LET(_xlpm.cf3757_STANDARDAddresses, GetSheetLocationAddresses(ClassFeed3757_STANDARDTracker, ClassFeed3757_STANDARDErrors), _xlpm.cf6161_STANDARDAddresses, GetSheetLocationAddresses(ClassFeed6161_STANDARDTracker, ClassFeed6161_STANDARDErrors), _xlpm.stackedAddresses, _xlfn.VSTACK(_xlpm.cf3757_STANDARDAddresses, _xlpm.cf6161_STANDARDAddresses), _xlfn._xlws.FILTER(_xlpm.stackedAddresses, _xlpm.stackedAddresses<>"", ""))} -> 0
B4: =IF(AND(C4<>"", H4<>""), HYPERLINK("#'" & C4 & "'!" & H4, H4), "") -> 0
B5: =IF(AND(C5<>"", H5<>""), HYPERLINK("#'" & C5 & "'!" & H5, H5), "") -> 0
B6: =IF(AND(C6<>"", H6<>""), HYPERLINK("#'" & C6 & "'!" & H6, H6), "") -> 0
B7: =IF(AND(C7<>"", H7<>""), HYPERLINK("#'" & C7 & "'!" & H7, H7), "") -> 0
B8: =IF(AND(C8<>"", H8<>""), HYPERLINK("#'" & C8 & "'!" & H8, H8), "") -> 0
B9: =IF(AND(C9<>"", H9<>""), HYPERLINK("#'" & C9 & "'!" & H9, H9), "") -> 0
B10: =IF(AND(C10<>"", H10<>""), HYPERLINK("#'" & C10 & "'!" & H10, H10), "") -> 0
B11: =IF(AND(C11<>"", H11<>""), HYPERLINK("#'" & C11 & "'!" & H11, H11), "") -> 0
B12: =IF(AND(C12<>"", H12<>""), HYPERLINK("#'" & C12 & "'!" & H12, H12), "") -> 0
B13: =IF(AND(C13<>"", H13<>""), HYPERLINK("#'" & C13 & "'!" & H13, H13), "") -> 0
B14: =IF(AND(C14<>"", H14<>""), HYPERLINK("#'" & C14 & "'!" & H14, H14), "") -> 0
B15: =IF(AND(C15<>"", H15<>""), HYPERLINK("#'" & C15 & "'!" & H15, H15), "") -> 0
... B6002: =IF(AND(C6002<>"", H6002<>""), HYPERLINK("#'" & C6002 & "'!" & H6002, H6002), "") -> 0

Sheet 3757 - Wall Stickers (S)
B1: 9000 | C1: 9001 | D1: 9005 | E1: 9006 | F1: 9007 | G1: 9008 | H1: 9009 | I1: 9010 | J1: 9011 | K1: 9012 | L1: 9011 | M1: 9012 | N1: 9011 | O1: 9012 | P1: 9017 | Q1: 9070 | R1: 9018 | S1: 9019 | T1: 9020 | U1: 9021 | V1: 9021 | W1: 9021 | X1: 9021 | Y1: 9021 | Z1: 9021 | AA1: 9021 | AB1: 9021 | AC1: 9004 | AD1: 9026 | AE1: 9027 | AF1: 9028 | AG1: 9029 | AH1: 9030 | AI1: 9031 | AJ1: 9032 | AK1: 9033 | AL1: 9034 | AM1: 9035 | AN1: 9036 | AO1: 9037 | AP1: 9038 | AQ1: 9039 | AR1: 9040 | AS1: 9037 | AT1: 9038 | AU1: 9039 | AV1: 9040 | AW1: 9037 | AX1: 9038 | AY1: 9039 | AZ1: 9040 | BA1: 9037 | BB1: 9038 | BC1: 9039 | BD1: 9040 | BE1: 9037 | BF1: 9038 | BG1: 9039 | BH1: 9040 | BI1: 9037 | BJ1: 9038 | BK1: 9039 | BL1: 9040 | BM1: 9037 | BN1: 9038 | BO1: 9039 | BP1: 9040 | BQ1: 9037 | BR1: 9038 | BS1: 9039 | BT1: 9040 | BU1: 9037 | BV1: 9038 | BW1: 9039 | BX1: 9040 | BY1: 9037 | BZ1: 9038 | CA1: 9039 | CB1: 9040 | CC1: 9037 | CD1: 9038 | CE1: 9039 | CF1: 9040 | CG1: 9037 | CH1: 9038 | CI1: 9039 | CJ1: 9040 | CK1: 9037 | CL1: 9038 | CM1: 9039 | CN1: 9040 | CO1: 9037 | CP1: 9038 | CQ1: 9039 | CR1: 9040 | CS1: 9037 | CT1: 9038 | CU1: 9039 | CV1: 9040 | CW1: 9037 | CX1: 9038 | CY1: 9039 | CZ1: 9040 | DA1: 9037 | DB1: 9038 | DC1: 9039 | DD1: 9040 | DE1: 9037 | DF1: 9038 | DG1: 9039 | DH1: 9040 | DI1: 9037 | DJ1: 9038 | DK1: 9039 | DL1: 9040 | DM1: 9037 | DN1: 9038 | DO1: 9039 | DP1: 9040 | DQ1: 9037 | DR1: 9038 | DS1: 9039 | DT1: 9040 | DU1: 9037 | DV1: 9038 | DW1: 9039 | DX1: 9040 | DY1: 9037 | DZ1: 9038 | EA1: 9039 | EB1: 9040 | EC1: 9037 | ED1: 9038 | EE1: 9039 | EF1: 9040 | EG1: 9037 | EH1: 9038 | EI1: 9039 | EJ1: 9040 | EK1: 9037 | EL1: 9038 | EM1: 9039 | EN1: 9040 | EO1: 9037 | EP1: 9038 | EQ1: 9039 | ER1: 9040 | ES1: 9037 | ET1: 9038 | EU1: 9039 | EV1: 9040 | EW1: 9037 | EX1: 9038 | EY1: 9039 | EZ1: 9040 | FA1: 9037 | FB1: 9038 | FC1: 9039 | FD1: 9040 | FE1: 9037 | FF1: 9038 | FG1: 9039 | FH1: 9040 | FI1: 9037 | FJ1: 9038 | FK1: 9039 | FL1: 9040 | FM1: 9037 | FN1: 9038 | FO1: 9039 | FP1: 9040 | FQ1: 9037 | FR1: 9038 | FS1: 9039 | FT1: 9040 | FU1: 9037 | FV1: 9038 | FW1: 9039 | FX1: 9040 | FY1: 9037 | FZ1: 9038 | GA1: 9039 | GB1: 9040 | GC1: 9037 | GD1: 9038 | GE1: 9039 | GF1: 9040 | GG1: 9037 | GH1: 9038 | GI1: 9039 | GJ1: 9040 | GK1: 9037 | GL1: 9038 | GM1: 9039 | GN1: 9040 | GO1: 9037 | GP1: 9038 | GQ1: 9039 | GR1: 9040 | GS1: 647 | GT1: 9041 | GU1: 9042 | GV1: 9043 | GW1: 9042 | GX1: 9043 | GY1: 9042 | GZ1: 9043 | HA1: 9042 | HB1: 9043 | HC1: 9042 | HD1: 9043 | HE1: 9053 | HF1: 9053 | HG1: 9053 | HH1: 9053 | HI1: 9053 | HJ1: 9053 | HK1: 9053 | HL1: 9053 | HM1: 9053 | HN1: 9053 | HO1: 9053 | HP1: 9053 | HQ1: 9053 | HR1: 9053 | HS1: 9053 | HT1: 9053 | HU1: 9053 | HV1: 9053 | HW1: 9053 | HX1: 9053 | HY1: 9053 | HZ1: 9053 | IA1: 9053 | IB1: 9053 | IC1: 9053 | ID1: 9053 | IE1: 9053 | IF1: 9053 | IG1: 9053 | IH1: 9053 | II1: 9058 | IJ1: 9058 | IK1: 9063 | IL1: 9064 | IM1: 9065 | IN1: 9066 | IO1: 9063 | IP1: 9064 | IQ1: 9065 | IR1: 9066 | IS1: 9063 | IT1: 9064 | IU1: 9065 | IV1: 9066 | IW1: 9063 | IX1: 9064 | IY1: 9065 | IZ1: 9066 | JA1: 9063 | JB1: 9064 | JC1: 9065 | JD1: 9066 | JE1: 9063 | JF1: 9064 | JG1: 9065 | JH1: 9066 | JI1: 9063 | JJ1: 9064 | JK1: 9065 | JL1: 9066 | JM1: 9063 | JN1: 9064 | JO1: 9065 | JP1: 9066 | JQ1: 9063 | JR1: 9064 | JS1: 9065 | JT1: 9066 | JU1: 9063 | JV1: 9064 | JW1: 9065 | JX1: 9066 | JY1: 6109 | JZ1: 1966 | KA1: 1217 | KB1: 2385 | KC1: 3538 | KD1: 2389 | KE1: 1560 | KF1: 137 | KG1: 95 | KH1: 807 | KI1: 1379 | KJ1: 1437 | KK1: 1567 | KL1: 1316 | KM1: 521 | KN1: 6253 | KO1: 1388 | KP1: 8653 | KQ1: 1557 | KR1: 769 | KS1: 770 | KT1: 264 | KU1: 28 | KV1: 135 | KW1: 256 | KX1: 31 | KY1: 117 | KZ1: 8205 | LA1: 8462
J2: 1 | K2: 1 | L2: 2 | M2: 2 | N2: 3 | O2: 3 | U2: 1 | V2: 2 | W2: 3 | X2: 4 | Y2: 5 | Z2: 6 | AA2: 7 | AB2: 8 | AO2: 1 | AP2: 1 | AQ2: 1 | AR2: 1 | AS2: 2 | AT2: 2 | AU2: 2 | AV2: 2 | AW2: 3 | AX2: 3 | AY2: 3 | AZ2: 3 | BA2: 4 | BB2: 4 | BC2: 4 | BD2: 4 | BE2: 5 | BF2: 5 | BG2: 5 | BH2: 5 | BI2: 6 | BJ2: 6 | BK2: 6 | BL2: 6 | BM2: 7 | BN2: 7 | BO2: 7 | BP2: 7 | BQ2: 8 | BR2: 8 | BS2: 8 | BT2: 8 | BU2: 9 | BV2: 9 | BW2: 9 | BX2: 9 | BY2: 10 | BZ2: 10 | CA2: 10 | CB2: 10 | CC2: 11 | CD2: 11 | CE2: 11 | CF2: 11 | CG2: 12 | CH2: 12 | CI2: 12 | CJ2: 12 | CK2: 13 | CL2: 13 | CM2: 13 | CN2: 13 | CO2: 14 | CP2: 14 | CQ2: 14 | CR2: 14 | CS2: 15 | CT2: 15 | CU2: 15 | CV2: 15 | CW2: 16 | CX2: 16 | CY2: 16 | CZ2: 16 | DA2: 17 | DB2: 17 | DC2: 17 | DD2: 17 | DE2: 18 | DF2: 18 | DG2: 18 | DH2: 18 | DI2: 19 | DJ2: 19 | DK2: 19 | DL2: 19 | DM2: 20 | DN2: 20 | DO2: 20 | DP2: 20 | DQ2: 21 | DR2: 21 | DS2: 21 | DT2: 21 | DU2: 22 | DV2: 22 | DW2: 22 | DX2: 22 | DY2: 23 | DZ2: 23 | EA2: 23 | EB2: 23 | EC2: 24 | ED2: 24 | EE2: 24 | EF2: 24 | EG2: 25 | EH2: 25 | EI2: 25 | EJ2: 25 | EK2: 26 | EL2: 26 | EM2: 26 | EN2: 26 | EO2: 27 | EP2: 27 | EQ2: 27 | ER2: 27 | ES2: 28 | ET2: 28 | EU2: 28 | EV2: 28 | EW2: 29 | EX2: 29 | EY2: 29 | EZ2: 29 | FA2: 30 | FB2: 30 | FC2: 30 | FD2: 30 | FE2: 31 | FF2: 31 | FG2: 31 | FH2: 31 | FI2: 32 | FJ2: 32 | FK2: 32 | FL2: 32 | FM2: 33 | FN2: 33 | FO2: 33 | FP2: 33 | FQ2: 34 | FR2: 34 | FS2: 34 | FT2: 34 | FU2: 35 | FV2: 35 | FW2: 35 | FX2: 35 | FY2: 36 | FZ2: 36 | GA2: 36 | GB2: 36 | GC2: 37 | GD2: 37 | GE2: 37 | GF2: 37 | GG2: 38 | GH2: 38 | GI2: 38 | GJ2: 38 | GK2: 39 | GL2: 39 | GM2: 39 | GN2: 39 | GO2: 40 | GP2: 40 | GQ2: 40 | GR2: 40 | GU2: 1 | GV2: 1 | GW2: 2 | GX2: 2 | GY2: 3 | GZ2: 3 | HA2: 4 | HB2: 4 | HC2: 5 | HD2: 5 | HE2: 1 | HF2: 2 | HG2: 3 | HH2: 4 | HI2: 5 | HJ2: 6 | HK2: 7 | HL2: 8 | HM2: 9 | HN2: 10 | HO2: 11 | HP2: 12 | HQ2: 13 | HR2: 14 | HS2: 15 | HT2: 16 | HU2: 17 | HV2: 18 | HW2: 19 | HX2: 20 | HY2: 21 | HZ2: 22 | IA2: 23 | IB2: 24 | IC2: 25 | ID2: 26 | IE2: 27 | IF2: 28 | IG2: 29 | IH2: 30 | II2: 1 | IJ2: 2 | IK2: 1 | IL2: 1 | IM2: 1 | IN2: 1 | IO2: 2 | IP2: 2 | IQ2: 2 | IR2: 2 | IS2: 3 | IT2: 3 | IU2: 3 | IV2: 3 | IW2: 4 | IX2: 4 | IY2: 4 | IZ2: 4 | JA2: 5 | JB2: 5 | JC2: 5 | JD2: 5 | JE2: 6 | JF2: 6 | JG2: 6 | JH2: 6 | JI2: 7 | JJ2: 7 | JK2: 7 | JL2: 7 | JM2: 8 | JN2: 8 | JO2: 8 | JP2: 8 | JQ2: 9 | JR2: 9 | JS2: 9 | JT2: 9 | JU2: 10 | JV2: 10 | JW2: 10 | JX2: 10
B3: Basic Information | F3: Branding | H3: Variant Grouping | P3: Pricing | T3: Marketing Information | AC3: Fulfillment Information | AO3: Carton Details | GS3: Compliance | HE3: Media | JY3: Attributes
B4: Required | C4: Required | D4: Recommended | E4: Required | F4: Required | G4: Conditional | H4: Recommended | I4: Conditional | J4: Conditional | K4: Conditional | L4: Conditional | M4: Conditional | N4: Conditional | O4: Conditional | P4: Required | Q4: Additional | R4: Additional | S4: Additional | T4: Conditional | U4: Conditional | V4: Conditional | W4: Conditional | X4: Conditional | Y4: Conditional | Z4: Conditional | AA4: Conditional | AB4: Conditional | AC4: Additional | AD4: Required | AE4: Required | AF4: Required | AG4: Required | AH4: Required | AI4: Conditional | AJ4: Required | AK4: Required | AL4: Conditional | AM4: Conditional | AN4: Conditional | AO4: Required | AP4: Required | AQ4: Required | AR4: Required | AS4: Conditional | AT4: Conditional | AU4: Conditional | AV4: Conditional | AW4: Conditional | AX4: Conditional | AY4: Conditional | AZ4: Conditional | BA4: Conditional | BB4: Conditional | BC4: Conditional | BD4: Conditional | BE4: Conditional | BF4: Conditional | BG4: Conditional | BH4: Conditional | BI4: Conditional | BJ4: Conditional | BK4: Conditional | BL4: Conditional | BM4: Conditional | BN4: Conditional | BO4: Conditional | BP4: Conditional | BQ4: Conditional | BR4: Conditional | BS4: Conditional | BT4: Conditional | BU4: Conditional | BV4: Conditional | BW4: Conditional | BX4: Conditional | BY4: Conditional | BZ4: Conditional | CA4: Conditional | CB4: Conditional | CC4: Conditional | CD4: Conditional | CE4: Conditional | CF4: Conditional | CG4: Conditional | CH4: Conditional | CI4: Conditional | CJ4: Conditional | CK4: Conditional | CL4: Conditional | CM4: Conditional | CN4: Conditional | CO4: Conditional | CP4: Conditional | CQ4: Conditional | CR4: Conditional | CS4: Conditional | CT4: Conditional | CU4: Conditional | CV4: Conditional | CW4: Conditional | CX4: Conditional | CY4: Conditional | CZ4: Conditional | DA4: Conditional | DB4: Conditional | DC4: Conditional | DD4: Conditional | DE4: Conditional | DF4: Conditional | DG4: Conditional | DH4: Conditional | DI4: Conditional | DJ4: Conditional | DK4: Conditional | DL4: Conditional | DM4: Conditional | DN4: Conditional | DO4: Conditional | DP4: Conditional | DQ4: Conditional | DR4: Conditional | DS4: Conditional | DT4: Conditional | DU4: Conditional | DV4: Conditional | DW4: Conditional | DX4: Conditional | DY4: Conditional | DZ4: Conditional | EA4: Conditional | EB4: Conditional | EC4: Conditional | ED4: Conditional | EE4: Conditional | EF4: Conditional | EG4: Conditional | EH4: Conditional | EI4: Conditional | EJ4: Conditional | EK4: Conditional | EL4: Conditional | EM4: Conditional | EN4: Conditional | EO4: Conditional | EP4: Conditional | EQ4: Conditional | ER4: Conditional | ES4: Conditional | ET4: Conditional | EU4: Conditional | EV4: Conditional | EW4: Conditional | EX4: Conditional | EY4: Conditional | EZ4: Conditional | FA4: Conditional | FB4: Conditional | FC4: Conditional | FD4: Conditional | FE4: Conditional | FF4: Conditional | FG4: Conditional | FH4: Conditional | FI4: Conditional | FJ4: Conditional | FK4: Conditional | FL4: Conditional | FM4: Conditional | FN4: Conditional | FO4: Conditional | FP4: Conditional | FQ4: Conditional | FR4: Conditional | FS4: Conditional | FT4: Conditional | FU4: Conditional | FV4: Conditional | FW4: Conditional | FX4: Conditional | FY4: Conditional | FZ4: Conditional | GA4: Conditional | GB4: Conditional | GC4: Conditional | GD4: Conditional | GE4: Conditional | GF4: Conditional | GG4: Conditional | GH4: Conditional | GI4: Conditional | GJ4: Conditional | GK4: Conditional | GL4: Conditional | GM4: Conditional | GN4: Conditional | GO4: Conditional | GP4: Conditional | GQ4: Conditional | GR4: Conditional | GS4: Required | GT4: Required | GU4: Conditional | GV4: Conditional | GW4: Conditional | GX4: Conditional | GY4: Conditional | GZ4: Conditional | HA4: Conditional | HB4: Conditional | HC4: Conditional | HD4: Conditional | HE4: Required | HF4: Additional | HG4: Additional | HH4: Additional | HI4: Additional | HJ4: Additional | HK4: Additional | HL4: Additional | HM4: Additional | HN4: Additional | HO4: Additional | HP4: Additional | HQ4: Additional | HR4: Additional | HS4: Additional | HT4: Additional | HU4: Additional | HV4: Additional | HW4: Additional | HX4: Additional | HY4: Additional | HZ4: Additional | IA4: Additional | IB4: Additional | IC4: Additional | ID4: Additional | IE4: Additional | IF4: Additional | IG4: Additional | IH4: Additional | II4: Additional | IJ4: Additional | IK4: Conditional | IL4: Additional | IM4: Additional | IN4: Additional | IO4: Conditional | IP4: Additional | IQ4: Additional | IR4: Additional | IS4: Conditional | IT4: Additional | IU4: Additional | IV4: Additional | IW4: Conditional | IX4: Additional | IY4: Additional | IZ4: Additional | JA4: Conditional | JB4: Additional | JC4: Additional | JD4: Additional | JE4: Conditional | JF4: Additional | JG4: Additional | JH4: Additional | JI4: Conditional | JJ4: Additional | JK4: Additional | JL4: Additional | JM4: Conditional | JN4: Additional | JO4: Additional | JP4: Additional | JQ4: Conditional | JR4: Additional | JS4: Additional | JT4: Additional | JU4: Conditional | JV4: Additional | JW4: Additional | JX4: Additional | JY4: Required | JZ4: Recommended | KA4: Required | KB4: Required | KC4: Required | KD4: Recommended | KE4: Recommended | KF4: Recommended | KG4: Additional | KH4: Required | KI4: Recommended | KJ4: Recommended | KK4: Recommended | KL4: Required | KM4: Recommended | KN4: Required | KO4: Conditional | KP4: Recommended | KQ4: Recommended | KR4: Required | KS4: Required | KT4: Required | KU4: Recommended | KV4: Conditional | KW4: Recommended | KX4: Required | KY4: Required | KZ4: Recommended | LA4: Recommended
A5: Errors | B5: Supplier Part Number | C5: Manufacturer Part Number | D5: Universal Product Code | E5: Product Name | F5: Brand | G5: Collection Name | H5: Variant Type | I5: Group Reference ID | J5: Variant Grouping 1 | K5: Variant Attribute Name On Site 1 | L5: Variant Grouping 2 | M5: Variant Attribute Name On Site 2 | N5: Variant Grouping 3 | O5: Variant Attribute Name On Site 3 | P5: Base Cost | Q5: Everyday B2B Discount Rate | R5: Minimum Advertised Price | S5: Manufacturer Suggested Retail Price | T5: Marketing Copy | U5: Feature Bullet 1 | V5: Feature Bullet 2 | W5: Feature Bullet 3 | X5: Feature Bullet 4 | Y5: Feature Bullet 5 | Z5: Feature Bullet 6 | AA5: Feature Bullet 7 | AB5: Feature Bullet 8 | AC5: Amazon Seller SKU | AD5: Minimum Order Quantity | AE5: Force Quantity Multiplier | AF5: Display Set Quantity | AG5: Product Weight | AH5: Ship Type | AI5: Freight Class | AJ5: Lead Time | AK5: Replacement Lead Time | AL5: National Motor Freight Class | AM5: Flat Pack | AN5: Ship Palletized | AO5: Carton Weight 1 | AP5: Carton Height 1 | AQ5: Carton Width 1 | AR5: Carton Depth 1 | AS5: Carton Weight 2 | AT5: Carton Height 2 | AU5: Carton Width 2 | AV5: Carton Depth 2 | AW5: Carton Weight 3 | AX5: Carton Height 3 | AY5: Carton Width 3 | AZ5: Carton Depth 3 | BA5: Carton Weight 4 | BB5: Carton Height 4 | BC5: Carton Width 4 | BD5: Carton Depth 4 | BE5: Carton Weight 5 | BF5: Carton Height 5 | BG5: Carton Width 5 | BH5: Carton Depth 5 | BI5: Carton Weight 6 | BJ5: Carton Height 6 | BK5: Carton Width 6 | BL5: Carton Depth 6 | BM5: Carton Weight 7 | BN5: Carton Height 7 | BO5: Carton Width 7 | BP5: Carton Depth 7 | BQ5: Carton Weight 8 | BR5: Carton Height 8 | BS5: Carton Width 8 | BT5: Carton Depth 8 | BU5: Carton Weight 9 | BV5: Carton Height 9 | BW5: Carton Width 9 | BX5: Carton Depth 9 | BY5: Carton Weight 10 | BZ5: Carton Height 10 | CA5: Carton Width 10 | CB5: Carton Depth 10 | CC5: Carton Weight 11 | CD5: Carton Height 11 | CE5: Carton Width 11 | CF5: Carton Depth 11 | CG5: Carton Weight 12 | CH5: Carton Height 12 | CI5: Carton Width 12 | CJ5: Carton Depth 12 | CK5: Carton Weight 13 | CL5: Carton Height 13 | CM5: Carton Width 13 | CN5: Carton Depth 13 | CO5: Carton Weight 14 | CP5: Carton Height 14 | CQ5: Carton Width 14 | CR5: Carton Depth 14 | CS5: Carton Weight 15 | CT5: Carton Height 15 | CU5: Carton Width 15 | CV5: Carton Depth 15 | CW5: Carton Weight 16 | CX5: Carton Height 16 | CY5: Carton Width 16 | CZ5: Carton Depth 16 | DA5: Carton Weight 17 | DB5: Carton Height 17 | DC5: Carton Width 17 | DD5: Carton Depth 17 | DE5: Carton Weight 18 | DF5: Carton Height 18 | DG5: Carton Width 18 | DH5: Carton Depth 18 | DI5: Carton Weight 19 | DJ5: Carton Height 19 | DK5: Carton Width 19 | DL5: Carton Depth 19 | DM5: Carton Weight 20 | DN5: Carton Height 20 | DO5: Carton Width 20 | DP5: Carton Depth 20 | DQ5: Carton Weight 21 | DR5: Carton Height 21 | DS5: Carton Width 21 | DT5: Carton Depth 21 | DU5: Carton Weight 22 | DV5: Carton Height 22 | DW5: Carton Width 22 | DX5: Carton Depth 22 | DY5: Carton Weight 23 | DZ5: Carton Height 23 | EA5: Carton Width 23 | EB5: Carton Depth 23 | EC5: Carton Weight 24 | ED5: Carton Height 24 | EE5: Carton Width 24 | EF5: Carton Depth 24 | EG5: Carton Weight 25 | EH5: Carton Height 25 | EI5: Carton Width 25 | EJ5: Carton Depth 25 | EK5: Carton Weight 26 | EL5: Carton Height 26 | EM5: Carton Width 26 | EN5: Carton Depth 26 | EO5: Carton Weight 27 | EP5: Carton Height 27 | EQ5: Carton Width 27 | ER5: Carton Depth 27 | ES5: Carton Weight 28 | ET5: Carton Height 28 | EU5: Carton Width 28 | EV5: Carton Depth 28 | EW5: Carton Weight 29 | EX5: Carton Height 29 | EY5: Carton Width 29 | EZ5: Carton Depth 29 | FA5: Carton Weight 30 | FB5: Carton Height 30 | FC5: Carton Width 30 | FD5: Carton Depth 30 | FE5: Carton Weight 31 | FF5: Carton Height 31 | FG5: Carton Width 31 | FH5: Carton Depth 31 | FI5: Carton Weight 32 | FJ5: Carton Height 32 | FK5: Carton Width 32 | FL5: Carton Depth 32 | FM5: Carton Weight 33 | FN5: Carton Height 33 | FO5: Carton Width 33 | FP5: Carton Depth 33 | FQ5: Carton Weight 34 | FR5: Carton Height 34 | FS5: Carton Width 34 | FT5: Carton Depth 34 | FU5: Carton Weight 35 | FV5: Carton Height 35 | FW5: Carton Width 35 | FX5: Carton Depth 35 | FY5: Carton Weight 36 | FZ5: Carton Height 36 | GA5: Carton Width 36 | GB5: Carton Depth 36 | GC5: Carton Weight 37 | GD5: Carton Height 37 | GE5: Carton Width 37 | GF5: Carton Depth 37 | GG5: Carton Weight 38 | GH5: Carton Height 38 | GI5: Carton Width 38 | GJ5: Carton Depth 38 | GK5: Carton Weight 39 | GL5: Carton Height 39 | GM5: Carton Width 39 | GN5: Carton Depth 39 | GO5: Carton Weight 40 | GP5: Carton Height 40 | GQ5: Carton Width 40 | GR5: Carton Depth 40 | GS5: Country of Origin | GT5: Warning Required | GU5: Chemical 1 | GV5: Toxicity 1 | GW5: Chemical 2 | GX5: Toxicity 2 | GY5: Chemical 3 | GZ5: Toxicity 3 | HA5: Chemical 4 | HB5: Toxicity 4 | HC5: Chemical 5 | HD5: Toxicity 5 | HE5: Image File Name or URL 1 | HF5: Image File Name or URL 2 | HG5: Image File Name or URL 3 | HH5: Image File Name or URL 4 | HI5: Image File Name or URL 5 | HJ5: Image File Name or URL 6 | HK5: Image File Name or URL 7 | HL5: Image File Name or URL 8 | HM5: Image File Name or URL 9 | HN5: Image File Name or URL 10 | HO5: Image File Name or URL 11 | HP5: Image File Name or URL 12 | HQ5: Image File Name or URL 13 | HR5: Image File Name or URL 14 | HS5: Image File Name or URL 15 | HT5: Image File Name or URL 16 | HU5: Image File Name or URL 17 | HV5: Image File Name or URL 18 | HW5: Image File Name or URL 19 | HX5: Image File Name or URL 20 | HY5: Image File Name or URL 21 | HZ5: Image File Name or URL 22 | IA5: Image File Name or URL 23 | IB5: Image File Name or URL 24 | IC5: Image File Name or URL 25 | ID5: Image File Name or URL 26 | IE5: Image File Name or URL 27 | IF5: Image File Name or URL 28 | IG5: Image File Name or URL 29 | IH5: Image File Name or URL 30 | II5: Video File Name or URL 1 | IJ5: Video File Name or URL 2 | IK5: Document File Name or URL 1 | IL5: Document Type 1 | IM5: Legal Document Type 1 | IN5: Document Region 1 | IO5: Document File Name or URL 2 | IP5: Document Type 2 | IQ5: Legal Document Type 2 | IR5: Document Region 2 | IS5: Document File Name or URL 3 | IT5: Document Type 3 | IU5: Legal Document Type 3 | IV5: Document Region 3 | IW5: Document File Name or URL 4 | IX5: Document Type 4 | IY5: Legal Document Type 4 | IZ5: Document Region 4 | JA5: Document File Name or URL 5 | JB5: Document Type 5 | JC5: Legal Document Type 5 | JD5: Document Region 5 | JE5: Document File Name or URL 6 | JF5: Document Type 6 | JG5: Legal Document Type 6 | JH5: Document Region 6 | JI5: Document File Name or URL 7 | JJ5: Document Type 7 | JK5: Legal Document Type 7 | JL5: Document Region 7 | JM5: Document File Name or URL 8 | JN5: Document Type 8 | JO5: Legal Document Type 8 | JP5: Document Region 8 | JQ5: Document File Name or URL 9 | JR5: Document Type 9 | JS5: Legal Document Type 9 | JT5: Document Region 9 | JU5: Document File Name or URL 10 | JV5: Document Type 10 | JW5: Legal Document Type 10 | JX5: Document Region 10 | JY5: Product Type | JZ5: Subject | KA5: Surface Type | KB5: Material | KC5: Compatible Surfaces | KD5: Personalization or Monogramming | KE5: Room Use | KF5: Holiday / Occasion | KG5: Country of Origin - Additional Details | KH5: BPA Free | KI5: Licensed Product Category | KJ5: Durability | KK5: Adjustability Features | KL5: Color | KM5: Total Number of Pieces Included | KN5: Pieces Included | KO5: Movie / Show Series Name | KP5: General Features | KQ5: Age Group | KR5: Overall Height - Top to Bottom | KS5: Overall Width - Side to Side | KT5: Overall Product Weight | KU5: Commercial Warranty | KV5: Commercial Warranty Length | KW5: Wayfair Compliance Vetting Program (including Baby Safety Alliance fka JPMA) for this product category | KX5: Uniform Packaging and Labeling Regulations (UPLR) Compliant | KY5: Canada Product Restriction | KZ5: ISTA Certified | LA5: Sustainability & Social Responsibility Certifications (North America Only)
A6: Displays the error status and message for the first error in the row, with a link to the corresponding cell. | B6: Your part number (up to 64 characters) that must be unique. This value appears on your Inventory Feed and Purchased Orders. | C6: This is the part number provided by the manufacturer. Up to 64 characters. Must be unique. | D6: UPC (must be a unique value that follows the standard format). | E6: 254 character limit; do not use abbreviations. Wayfair may update the name based on marketing standards. | F6: Enter the product's brand. New brands must be created in the brand management tool before you can select them. | G6: If your product is part of a collection of associated products, enter the collection name here. For example, a bed and a nightstand can belong to the same collection, but a bed that comes in two different colors cannot. (Use Variant Grouping instead.) Products in a collection will have separate listings on the site. | H6: Indicate whether this part number is a standalone product, primary variant (all required fields must be provided), or non-primary variant (data can be autofilled from primary variant). | I6: Provide an identifier to group your variants. This information will be used to create a listing. | J6: Common attribute to group products by. Select from dropdown or enter a custom value. | K6: Display name for variant attribute, if differs from corresponding Attribute answer. | L6: Common attribute to group products by. Select from dropdown or enter a custom value. | M6: Display name for variant attribute, if differs from corresponding Attribute answer. | N6: Common attribute to group products by. Select from dropdown or enter a custom value. | O6: Display name for variant attribute, if differs from corresponding Attribute answer. | P6: Your supplier profile preference for currency is used to determine the currency of the base (wholesale) cost provided. | Q6: Business-to-business discount rate for everyday pricing (decimal). Region/currency context may apply similarly to other pricing fields on this sheet. | R6: The region selected for this sheet is used to determine the currency of the MAP provided. This may differ from the currency of your base cost. | S6: The region selected for this sheet is used to determine the currency of the MSRP provided. This may differ from the currency of your base cost. | T6: A product description up to 250 words is recommended. Please do not use special symbols (trademark, copyright, etc.) or extra lines/spacing. This should be a short, single paragraph product description in complete sentences highlighting details about key product information. | U6: 15 words or less, describing one aspect of the product, eg., Unique aspects, benefits, use cases, technology. These provide customers with key facts at first glance and help them to decide whether they want to make the purchase. If no marketing copy is provided, then at least 3 feature bullets must be provided. | V6: 15 words or less, describing one aspect of the product, eg., Unique aspects, benefits, use cases, technology. These provide customers with key facts at first glance and help them to decide whether they want to make the purchase. If no marketing copy is provided, then at least 3 feature bullets must be provided. | W6: 15 words or less, describing one aspect of the product, eg., Unique aspects, benefits, use cases, technology. These provide customers with key facts at first glance and help them to decide whether they want to make the purchase. If no marketing copy is provided, then at least 3 feature bullets must be provided. | X6: 15 words or less, describing one aspect of the product, eg., Unique aspects, benefits, use cases, technology. These provide customers with key facts at first glance and help them to decide whether they want to make the purchase. If no marketing copy is provided, then at least 3 feature bullets must be provided. | Y6: 15 words or less, describing one aspect of the product, eg., Unique aspects, benefits, use cases, technology. These provide customers with key facts at first glance and help them to decide whether they want to make the purchase. If no marketing copy is provided, then at least 3 feature bullets must be provided. | Z6: 15 words or less, describing one aspect of the product, eg., Unique aspects, benefits, use cases, technology. These provide customers with key facts at first glance and help them to decide whether they want to make the purchase. If no marketing copy is provided, then at least 3 feature bullets must be provided. | AA6: 15 words or less, describing one aspect of the product, eg., Unique aspects, benefits, use cases, technology. These provide customers with key facts at first glance and help them to decide whether they want to make the purchase. If no marketing copy is provided, then at least 3 feature bullets must be provided. | AB6: 15 words or less, describing one aspect of the product, eg., Unique aspects, benefits, use cases, technology. These provide customers with key facts at first glance and help them to decide whether they want to make the purchase. If no marketing copy is provided, then at least 3 feature bullets must be provided. | AC6: The Amazon Standard Identification Number (ASIN) is a 10-character alphanumeric unique identifier assigned by Amazon to a product. | AD6: The minimum count of items a customer must choose to purchase the product. | AE6: This represents how many items the customer must buy in increments of, or in addition to. For example, if the minimum quantity is 1 and the forced multiplier is 2, then the customer can only buy in quantities of 1, 3, 5, 7, 9, etc. | AF6: Number of items represented by the part number and wholesale price. For example, if you want to sell a bundle of pillows, and the part number and wholesale cost you provided represents that full bundle of pillows, then you would answer the Display Set Quantity question with how many pillows are in the bundle. | AG6: [Pounds] What is the total weight of this product once assembled? Please enter just the number (i.e. 45.5) without a unit of measurement. | AH6: Enter small parcel or LTL to indicate how the product can ship based on size and weight. | AI6: Each product falls into 1 of 18 classes determined by a product's 'transportability' and are crucial for calculating shipping cost. The field is required when ship type is LTL. | AJ6: [Hours] This is the length of time from receipt of PO to shipment from the warehouse. | AK6: [Hours] This is length of time from receipt of a replacement PO to shipment from the warehouse | AL6: 5 to 7 digit number in length (depending on any sub classification) that will identify what is shipping in the box | AM6: Also known as 'knocked down'. Select 'Yes' if this product ships disassembled in a flat pack box. | AN6: Select 'Yes' if this product ships on a pallet. | AO6: [Pounds] Enter in the shipping weight (i.e. 45.5) of the packaging used for the product. If the product ships in more than one box, this measurement is per box. | AP6: [Inches] Enter in the shipping height (i.e. 45.5) of the packaging used for the product. If the product ships in more than one box, this measurement is per box. | AQ6: [Inches] Enter in the shipping width (i.e. 45.5) of the packaging used for the product. If the product ships in more than one box, this measurement is per box. | AR6: [Inches] Enter in the shipping depth (i.e. 45.5) of the packaging used for the product. If the product ships in more than one box, this measurement is per box. | AS6: [Pounds] Enter in the shipping weight (i.e. 45.5) of the packaging used for the product. If the product ships in more than one box, this measurement is per box. | AT6: [Inches] Enter in the shipping height (i.e. 45.5) of the packaging used for the product. If the product ships in more than one box, this measurement is per box. | AU6: [Inches] Enter in the shipping width (i.e. 45.5) of the packaging used for the product. If the product ships in more than one box, this measurement is per box. | AV6: [Inches] Enter in the shipping depth (i.e. 45.5) of the packaging used for the product. If the product ships in more than one box, this measurement is per box. | AW6: [Pounds] Enter in the shipping weight (i.e. 45.5) of the packaging used for the product. If the product ships in more than one box, this measurement is per box. | AX6: [Inches] Enter in the shipping height (i.e. 45.5) of the packaging used for the product. If the product ships in more than one box, this measurement is per box. | AY6: [Inches] Enter in the shipping width (i.e. 45.5) of the packaging used for the product. If the product ships in more than one box, this measurement is per box. | AZ6: [Inches] Enter in the shipping depth (i.e. 45.5) of the packaging used for the product. If the product ships in more than one box, this measurement is per box. | BA6: [Pounds] Enter in the shipping weight (i.e. 45.5) of the packaging used for the product. If the product ships in more than one box, this measurement is per box. | BB6: [Inches] Enter in the shipping height (i.e. 45.5) of the packaging used for the product. If the product ships in more than one box, this measurement is per box. | BC6: [Inches] Enter in the shipping width (i.e. 45.5) of the packaging used for the product. If the product ships in more than one box, this measurement is per box. | BD6: [Inches] Enter in the shipping depth (i.e. 45.5) of the packaging used for the product. If the product ships in more than one box, this measurement is per box. | BE6: [Pounds] Enter in the shipping weight (i.e. 45.5) of the packaging used for the product. If the product ships in more than one box, this measurement is per box. | BF6: [Inches] Enter in the shipping height (i.e. 45.5) of the packaging used for the product. If the product ships in more than one box, this measurement is per box. | BG6: [Inches] Enter in the shipping width (i.e. 45.5) of the packaging used for the product. If the product ships in more than one box, this measurement is per box. | BH6: [Inches] Enter in the shipping depth (i.e. 45.5) of the packaging used for the product. If the product ships in more than one box, this measurement is per box. | BI6: [Pounds] Enter in the shipping weight (i.e. 45.5) of the packaging used for the product. If the product ships in more than one box, this measurement is per box. | BJ6: [Inches] Enter in the shipping height (i.e. 45.5) of the packaging used for the product. If the product ships in more than one box, this measurement is per box. | BK6: [Inches] Enter in the shipping width (i.e. 45.5) of the packaging used for the product. If the product ships in more than one box, this measurement is per box. | BL6: [Inches] Enter in the shipping depth (i.e. 45.5) of the packaging used for the product. If the product ships in more than one box, this measurement is per box. | BM6: [Pounds] Enter in the shipping weight (i.e. 45.5) of the packaging used for the product. If the product ships in more than one box, this measurement is per box. | BN6: [Inches] Enter in the shipping height (i.e. 45.5) of the packaging used for the product. If the product ships in more than one box, this measurement is per box. | BO6: [Inches] Enter in the shipping width (i.e. 45.5) of the packaging used for the product. If the product ships in more than one box, this measurement is per box. | BP6: [Inches] Enter in the shipping depth (i.e. 45.5) of the packaging used for the product. If the product ships in more than one box, this measurement is per box. | BQ6: [Pounds] Enter in the shipping weight (i.e. 45.5) of the packaging used for the product. If the product ships in more than one box, this measurement is per box. | BR6: [Inches] Enter in the shipping height (i.e. 45.5) of the packaging used for the product. If the product ships in more than one box, this measurement is per box. | BS6: [Inches] Enter in the shipping width (i.e. 45.5) of the packaging used for the product. If the product ships in more than one box, this measurement is per box. | BT6: [Inches] Enter in the shipping depth (i.e. 45.5) of the packaging used for the product. If the product ships in more than one box, this measurement is per box. | BU6: [Pounds] Enter in the shipping weight (i.e. 45.5) of the packaging used for the product. If the product ships in more than one box, this measurement is per box. | BV6: [Inches] Enter in the shipping height (i.e. 45.5) of the packaging used for the product. If the product ships in more than one box, this measurement is per box. | BW6: [Inches] Enter in the shipping width (i.e. 45.5) of the packaging used for the product. If the product ships in more than one box, this measurement is per box. | BX6: [Inches] Enter in the shipping depth (i.e. 45.5) of the packaging used for the product. If the product ships in more than one box, this measurement is per box. | BY6: [Pounds] Enter in the shipping weight (i.e. 45.5) of the packaging used for the product. If the product ships in more than one box, this measurement is per box. | BZ6: [Inches] Enter in the shipping height (i.e. 45.5) of the packaging used for the product. If the product ships in more than one box, this measurement is per box. | CA6: [Inches] Enter in the shipping width (i.e. 45.5) of the packaging used for the product. If the product ships in more than one box, this measurement is per box. | CB6: [Inches] Enter in the shipping depth (i.e. 45.5) of the packaging used for the product. If the product ships in more than one box, this measurement is per box. | CC6: [Pounds] Enter in the shipping weight (i.e. 45.5) of the packaging used for the product. If the product ships in more than one box, this measurement is per box. | CD6: [Inches] Enter in the shipping height (i.e. 45.5) of the packaging used for the product. If the product ships in more than one box, this measurement is per box. | CE6: [Inches] Enter in the shipping width (i.e. 45.5) of the packaging used for the product. If the product ships in more than one box, this measurement is per box. | CF6: [Inches] Enter in the shipping depth (i.e. 45.5) of the packaging used for the product. If the product ships in more than one box, this measurement is per box. | CG6: [Pounds] Enter in the shipping weight (i.e. 45.5) of the packaging used for the product. If the product ships in more than one box, this measurement is per box. | CH6: [Inches] Enter in the shipping height (i.e. 45.5) of the packaging used for the product. If the product ships in more than one box, this measurement is per box. | CI6: [Inches] Enter in the shipping width (i.e. 45.5) of the packaging used for the product. If the product ships in more than one box, this measurement is per box. | CJ6: [Inches] Enter in the shipping depth (i.e. 45.5) of the packaging used for the product. If the product ships in more than one box, this measurement is per box. | CK6: [Pounds] Enter in the shipping weight (i.e. 45.5) of the packaging used for the product. If the product ships in more than one box, this measurement is per box. | CL6: [Inches] Enter in the shipping height (i.e. 45.5) of the packaging used for the product. If the product ships in more than one box, this measurement is per box. | CM6: [Inches] Enter in the shipping width (i.e. 45.5) of the packaging used for the product. If the product ships in more than one box, this measurement is per box. | CN6: [Inches] Enter in the shipping depth (i.e. 45.5) of the packaging used for the product. If the product ships in more than one box, this measurement is per box. | CO6: [Pounds] Enter in the shipping weight (i.e. 45.5) of the packaging used for the product. If the product ships in more than one box, this measurement is per box. | CP6: [Inches] Enter in the shipping height (i.e. 45.5) of the packaging used for the product. If the product ships in more than one box, this measurement is per box. | CQ6: [Inches] Enter in the shipping width (i.e. 45.5) of the packaging used for the product. If the product ships in more than one box, this measurement is per box. | CR6: [Inches] Enter in the shipping depth (i.e. 45.5) of the packaging used for the product. If the product ships in more than one box, this measurement is per box. | CS6: [Pounds] Enter in the shipping weight (i.e. 45.5) of the packaging used for the product. If the product ships in more than one box, this measurement is per box. | CT6: [Inches] Enter in the shipping height (i.e. 45.5) of the packaging used for the product. If the product ships in more than one box, this measurement is per box. | CU6: [Inches] Enter in the shipping width (i.e. 45.5) of the packaging used for the product. If the product ships in more than one box, this measurement is per box. | CV6: [Inches] Enter in the shipping depth (i.e. 45.5) of the packaging used for the product. If the product ships in more than one box, this measurement is per box. | CW6: [Pounds] Enter in the shipping weight (i.e. 45.5) of the packaging used for the product. If the product ships in more than one box, this measurement is per box. | CX6: [Inches] Enter in the shipping height (i.e. 45.5) of the packaging used for the product. If the product ships in more than one box, this measurement is per box. | CY6: [Inches] Enter in the shipping width (i.e. 45.5) of the packaging used for the product. If the product ships in more than one box, this measurement is per box. | CZ6: [Inches] Enter in the shipping depth (i.e. 45.5) of the packaging used for the product. If the product ships in more than one box, this measurement is per box. | DA6: [Pounds] Enter in the shipping weight (i.e. 45.5) of the packaging used for the product. If the product ships in more than one box, this measurement is per box. | DB6: [Inches] Enter in the shipping height (i.e. 45.5) of the packaging used for the product. If the product ships in more than one box, this measurement is per box. | DC6: [Inches] Enter in the shipping width (i.e. 45.5) of the packaging used for the product. If the product ships in more than one box, this measurement is per box. | DD6: [Inches] Enter in the shipping depth (i.e. 45.5) of the packaging used for the product. If the product ships in more than one box, this measurement is per box. | DE6: [Pounds] Enter in the shipping weight (i.e. 45.5) of the packaging used for the product. If the product ships in more than one box, this measurement is per box. | DF6: [Inches] Enter in the shipping height (i.e. 45.5) of the packaging used for the product. If the product ships in more than one box, this measurement is per box. | DG6: [Inches] Enter in the shipping width (i.e. 45.5) of the packaging used for the product. If the product ships in more than one box, this measurement is per box. | DH6: [Inches] Enter in the shipping depth (i.e. 45.5) of the packaging used for the product. If the product ships in more than one box, this measurement is per box. | DI6: [Pounds] Enter in the shipping weight (i.e. 45.5) of the packaging used for the product. If the product ships in more than one box, this measurement is per box. | DJ6: [Inches] Enter in the shipping height (i.e. 45.5) of the packaging used for the product. If the product ships in more than one box, this measurement is per box. | DK6: [Inches] Enter in the shipping width (i.e. 45.5) of the packaging used for the product. If the product ships in more than one box, this measurement is per box. | DL6: [Inches] Enter in the shipping depth (i.e. 45.5) of the packaging used for the product. If the product ships in more than one box, this measurement is per box. | DM6: [Pounds] Enter in the shipping weight (i.e. 45.5) of the packaging used for the product. If the product ships in more than one box, this measurement is per box. | DN6: [Inches] Enter in the shipping height (i.e. 45.5) of the packaging used for the product. If the product ships in more than one box, this measurement is per box. | DO6: [Inches] Enter in the shipping width (i.e. 45.5) of the packaging used for the product. If the product ships in more than one box, this measurement is per box. | DP6: [Inches] Enter in the shipping depth (i.e. 45.5) of the packaging used for the product. If the product ships in more than one box, this measurement is per box. | DQ6: [Pounds] Enter in the shipping weight (i.e. 45.5) of the packaging used for the product. If the product ships in more than one box, this measurement is per box. | DR6: [Inches] Enter in the shipping height (i.e. 45.5) of the packaging used for the product. If the product ships in more than one box, this measurement is per box. | DS6: [Inches] Enter in the shipping width (i.e. 45.5) of the packaging used for the product. If the product ships in more than one box, this measurement is per box. | DT6: [Inches] Enter in the shipping depth (i.e. 45.5) of the packaging used for the product. If the product ships in more than one box, this measurement is per box. | DU6: [Pounds] Enter in the shipping weight (i.e. 45.5) of the packaging used for the product. If the product ships in more than one box, this measurement is per box. | DV6: [Inches] Enter in the shipping height (i.e. 45.5) of the packaging used for the product. If the product ships in more than one box, this measurement is per box. | DW6: [Inches] Enter in the shipping width (i.e. 45.5) of the packaging used for the product. If the product ships in more than one box, this measurement is per box. | DX6: [Inches] Enter in the shipping depth (i.e. 45.5) of the packaging used for the product. If the product ships in more than one box, this measurement is per box. | DY6: [Pounds] Enter in the shipping weight (i.e. 45.5) of the packaging used for the product. If the product ships in more than one box, this measurement is per box. | DZ6: [Inches] Enter in the shipping height (i.e. 45.5) of the packaging used for the product. If the product ships in more than one box, this measurement is per box. | EA6: [Inches] Enter in the shipping width (i.e. 45.5) of the packaging used for the product. If the product ships in more than one box, this measurement is per box. | EB6: [Inches] Enter in the shipping depth (i.e. 45.5) of the packaging used for the product. If the product ships in more than one box, this measurement is per box. | EC6: [Pounds] Enter in the shipping weight (i.e. 45.5) of the packaging used for the product. If the product ships in more than one box, this measurement is per box. | ED6: [Inches] Enter in the shipping height (i.e. 45.5) of the packaging used for the product. If the product ships in more than one box, this measurement is per box. | EE6: [Inches] Enter in the shipping width (i.e. 45.5) of the packaging used for the product. If the product ships in more than one box, this measurement is per box. | EF6: [Inches] Enter in the shipping depth (i.e. 45.5) of the packaging used for the product. If the product ships in more than one box, this measurement is per box. | EG6: [Pounds] Enter in the shipping weight (i.e. 45.5) of the packaging used for the product. If the product ships in more than one box, this measurement is per box. | EH6: [Inches] Enter in the shipping height (i.e. 45.5) of the packaging used for the product. If the product ships in more than one box, this measurement is per box. | EI6: [Inches] Enter in the shipping width (i.e. 45.5) of the packaging used for the product. If the product ships in more than one box, this measurement is per box. | EJ6: [Inches] Enter in the shipping depth (i.e. 45.5) of the packaging used for the product. If the product ships in more than one box, this measurement is per box. | EK6: [Pounds] Enter in the shipping weight (i.e. 45.5) of the packaging used for the product. If the product ships in more than one box, this measurement is per box. | EL6: [Inches] Enter in the shipping height (i.e. 45.5) of the packaging used for the product. If the product ships in more than one box, this measurement is per box. | EM6: [Inches] Enter in the shipping width (i.e. 45.5) of the packaging used for the product. If the product ships in more than one box, this measurement is per box. | EN6: [Inches] Enter in the shipping depth (i.e. 45.5) of the packaging used for the product. If the product ships in more than one box, this measurement is per box. | EO6: [Pounds] Enter in the shipping weight (i.e. 45.5) of the packaging used for the product. If the product ships in more than one box, this measurement is per box. | EP6: [Inches] Enter in the shipping height (i.e. 45.5) of the packaging used for the product. If the product ships in more than one box, this measurement is per box. | EQ6: [Inches] Enter in the shipping width (i.e. 45.5) of the packaging used for the product. If the product ships in more than one box, this measurement is per box. | ER6: [Inches] Enter in the shipping depth (i.e. 45.5) of the packaging used for the product. If the product ships in more than one box, this measurement is per box. | ES6: [Pounds] Enter in the shipping weight (i.e. 45.5) of the packaging used for the product. If the product ships in more than one box, this measurement is per box. | ET6: [Inches] Enter in the shipping height (i.e. 45.5) of the packaging used for the product. If the product ships in more than one box, this measurement is per box. | EU6: [Inches] Enter in the shipping width (i.e. 45.5) of the packaging used for the product. If the product ships in more than one box, this measurement is per box. | EV6: [Inches] Enter in the shipping depth (i.e. 45.5) of the packaging used for the product. If the product ships in more than one box, this measurement is per box. | EW6: [Pounds] Enter in the shipping weight (i.e. 45.5) of the packaging used for the product. If the product ships in more than one box, this measurement is per box. | EX6: [Inches] Enter in the shipping height (i.e. 45.5) of the packaging used for the product. If the product ships in more than one box, this measurement is per box. | EY6: [Inches] Enter in the shipping width (i.e. 45.5) of the packaging used for the product. If the product ships in more than one box, this measurement is per box. | EZ6: [Inches] Enter in the shipping depth (i.e. 45.5) of the packaging used for the product. If the product ships in more than one box, this measurement is per box. | FA6: [Pounds] Enter in the shipping weight (i.e. 45.5) of the packaging used for the product. If the product ships in more than one box, this measurement is per box. | FB6: [Inches] Enter in the shipping height (i.e. 45.5) of the packaging used for the product. If the product ships in more than one box, this measurement is per box. | FC6: [Inches] Enter in the shipping width (i.e. 45.5) of the packaging used for the product. If the product ships in more than one box, this measurement is per box. | FD6: [Inches] Enter in the shipping depth (i.e. 45.5) of the packaging used for the product. If the product ships in more than one box, this measurement is per box. | FE6: [Pounds] Enter in the shipping weight (i.e. 45.5) of the packaging used for the product. If the product ships in more than one box, this measurement is per box. | FF6: [Inches] Enter in the shipping height (i.e. 45.5) of the packaging used for the product. If the product ships in more than one box, this measurement is per box. | FG6: [Inches] Enter in the shipping width (i.e. 45.5) of the packaging used for the product. If the product ships in more than one box, this measurement is per box. | FH6: [Inches] Enter in the shipping depth (i.e. 45.5) of the packaging used for the product. If the product ships in more than one box, this measurement is per box. | FI6: [Pounds] Enter in the shipping weight (i.e. 45.5) of the packaging used for the product. If the product ships in more than one box, this measurement is per box. | FJ6: [Inches] Enter in the shipping height (i.e. 45.5) of the packaging used for the product. If the product ships in more than one box, this measurement is per box. | FK6: [Inches] Enter in the shipping width (i.e. 45.5) of the packaging used for the product. If the product ships in more than one box, this measurement is per box. | FL6: [Inches] Enter in the shipping depth (i.e. 45.5) of the packaging used for the product. If the product ships in more than one box, this measurement is per box. | FM6: [Pounds] Enter in the shipping weight (i.e. 45.5) of the packaging used for the product. If the product ships in more than one box, this measurement is per box. | FN6: [Inches] Enter in the shipping height (i.e. 45.5) of the packaging used for the product. If the product ships in more than one box, this measurement is per box. | FO6: [Inches] Enter in the shipping width (i.e. 45.5) of the packaging used for the product. If the product ships in more than one box, this measurement is per box. | FP6: [Inches] Enter in the shipping depth (i.e. 45.5) of the packaging used for the product. If the product ships in more than one box, this measurement is per box. | FQ6: [Pounds] Enter in the shipping weight (i.e. 45.5) of the packaging used for the product. If the product ships in more than one box, this measurement is per box. | FR6: [Inches] Enter in the shipping height (i.e. 45.5) of the packaging used for the product. If the product ships in more than one box, this measurement is per box. | FS6: [Inches] Enter in the shipping width (i.e. 45.5) of the packaging used for the product. If the product ships in more than one box, this measurement is per box. | FT6: [Inches] Enter in the shipping depth (i.e. 45.5) of the packaging used for the product. If the product ships in more than one box, this measurement is per box. | FU6: [Pounds] Enter in the shipping weight (i.e. 45.5) of the packaging used for the product. If the product ships in more than one box, this measurement is per box. | FV6: [Inches] Enter in the shipping height (i.e. 45.5) of the packaging used for the product. If the product ships in more than one box, this measurement is per box. | FW6: [Inches] Enter in the shipping width (i.e. 45.5) of the packaging used for the product. If the product ships in more than one box, this measurement is per box. | FX6: [Inches] Enter in the shipping depth (i.e. 45.5) of the packaging used for the product. If the product ships in more than one box, this measurement is per box. | FY6: [Pounds] Enter in the shipping weight (i.e. 45.5) of the packaging used for the product. If the product ships in more than one box, this measurement is per box. | FZ6: [Inches] Enter in the shipping height (i.e. 45.5) of the packaging used for the product. If the product ships in more than one box, this measurement is per box. | GA6: [Inches] Enter in the shipping width (i.e. 45.5) of the packaging used for the product. If the product ships in more than one box, this measurement is per box. | GB6: [Inches] Enter in the shipping depth (i.e. 45.5) of the packaging used for the product. If the product ships in more than one box, this measurement is per box. | GC6: [Pounds] Enter in the shipping weight (i.e. 45.5) of the packaging used for the product. If the product ships in more than one box, this measurement is per box. | GD6: [Inches] Enter in the shipping height (i.e. 45.5) of the packaging used for the product. If the product ships in more than one box, this measurement is per box. | GE6: [Inches] Enter in the shipping width (i.e. 45.5) of the packaging used for the product. If the product ships in more than one box, this measurement is per box. | GF6: [Inches] Enter in the shipping depth (i.e. 45.5) of the packaging used for the product. If the product ships in more than one box, this measurement is per box. | GG6: [Pounds] Enter in the shipping weight (i.e. 45.5) of the packaging used for the product. If the product ships in more than one box, this measurement is per box. | GH6: [Inches] Enter in the shipping height (i.e. 45.5) of the packaging used for the product. If the product ships in more than one box, this measurement is per box. | GI6: [Inches] Enter in the shipping width (i.e. 45.5) of the packaging used for the product. If the product ships in more than one box, this measurement is per box. | GJ6: [Inches] Enter in the shipping depth (i.e. 45.5) of the packaging used for the product. If the product ships in more than one box, this measurement is per box. | GK6: [Pounds] Enter in the shipping weight (i.e. 45.5) of the packaging used for the product. If the product ships in more than one box, this measurement is per box. | GL6: [Inches] Enter in the shipping height (i.e. 45.5) of the packaging used for the product. If the product ships in more than one box, this measurement is per box. | GM6: [Inches] Enter in the shipping width (i.e. 45.5) of the packaging used for the product. If the product ships in more than one box, this measurement is per box. | GN6: [Inches] Enter in the shipping depth (i.e. 45.5) of the packaging used for the product. If the product ships in more than one box, this measurement is per box. | GO6: [Pounds] Enter in the shipping weight (i.e. 45.5) of the packaging used for the product. If the product ships in more than one box, this measurement is per box. | GP6: [Inches] Enter in the shipping height (i.e. 45.5) of the packaging used for the product. If the product ships in more than one box, this measurement is per box. | GQ6: [Inches] Enter in the shipping width (i.e. 45.5) of the packaging used for the product. If the product ships in more than one box, this measurement is per box. | GR6: [Inches] Enter in the shipping depth (i.e. 45.5) of the packaging used for the product. If the product ships in more than one box, this measurement is per box. | GS6: What is the country where this finished product was produced? For goods produced in more than one country where did it undergo the last substantial processing resulting in the finished item? If this is an imported good this is the Country of Origin that was declared to US Customs Service. If this product does not fit any of the listed options, please enter the correct country. | GT6: If the product requires a warning for Proposition 65 compliance in California, answer 'Yes' and indicate which chemicals and toxicities are applicable. | GU6: Select the chemical that requires the Prop65 warning. | GV6: Select the toxicity that can result from the selected chemical. | GW6: Select the chemical that requires the Prop65 warning. | GX6: Select the toxicity that can result from the selected chemical. | GY6: Select the chemical that requires the Prop65 warning. | GZ6: Select the toxicity that can result from the selected chemical. | HA6: Select the chemical that requires the Prop65 warning. | HB6: Select the toxicity that can result from the selected chemical. | HC6: Select the chemical that requires the Prop65 warning. | HD6: Select the toxicity that can result from the selected chemical. | HE6: Your first image will be set as the lead image for this listing, however, is subject to change upon Wayfair review. For each image uploaded, provide the file name with extension (e.g. PART_1.jpeg) or a direct public URL which leads to a single image (tip: to isolate the image, right click + select Open Image in New Tab). Elements like logos, buttons, etc will interfere with our ability to download the image. Do not exceed 20 images per product. | HF6: Your first image will be set as the lead image for this listing, however, is subject to change upon Wayfair review. For each image uploaded, provide the file name with extension (e.g. PART_1.jpeg) or a direct public URL which leads to a single image (tip: to isolate the image, right click + select Open Image in New Tab). Elements like logos, buttons, etc will interfere with our ability to download the image. Do not exceed 20 images per product. | HG6: Your first image will be set as the lead image for this listing, however, is subject to change upon Wayfair review. For each image uploaded, provide the file name with extension (e.g. PART_1.jpeg) or a direct public URL which leads to a single image (tip: to isolate the image, right click + select Open Image in New Tab). Elements like logos, buttons, etc will interfere with our ability to download the image. Do not exceed 20 images per product. | HH6: Your first image will be set as the lead image for this listing, however, is subject to change upon Wayfair review. For each image uploaded, provide the file name with extension (e.g. PART_1.jpeg) or a direct public URL which leads to a single image (tip: to isolate the image, right click + select Open Image in New Tab). Elements like logos, buttons, etc will interfere with our ability to download the image. Do not exceed 20 images per product. | HI6: Your first image will be set as the lead image for this listing, however, is subject to change upon Wayfair review. For each image uploaded, provide the file name with extension (e.g. PART_1.jpeg) or a direct public URL which leads to a single image (tip: to isolate the image, right click + select Open Image in New Tab). Elements like logos, buttons, etc will interfere with our ability to download the image. Do not exceed 20 images per product. | HJ6: Your first image will be set as the lead image for this listing, however, is subject to change upon Wayfair review. For each image uploaded, provide the file name with extension (e.g. PART_1.jpeg) or a direct public URL which leads to a single image (tip: to isolate the image, right click + select Open Image in New Tab). Elements like logos, buttons, etc will interfere with our ability to download the image. Do not exceed 20 images per product. | HK6: Your first image will be set as the lead image for this listing, however, is subject to change upon Wayfair review. For each image uploaded, provide the file name with extension (e.g. PART_1.jpeg) or a direct public URL which leads to a single image (tip: to isolate the image, right click + select Open Image in New Tab). Elements like logos, buttons, etc will interfere with our ability to download the image. Do not exceed 20 images per product. | HL6: Your first image will be set as the lead image for this listing, however, is subject to change upon Wayfair review. For each image uploaded, provide the file name with extension (e.g. PART_1.jpeg) or a direct public URL which leads to a single image (tip: to isolate the image, right click + select Open Image in New Tab). Elements like logos, buttons, etc will interfere with our ability to download the image. Do not exceed 20 images per product. | HM6: Your first image will be set as the lead image for this listing, however, is subject to change upon Wayfair review. For each image uploaded, provide the file name with extension (e.g. PART_1.jpeg) or a direct public URL which leads to a single image (tip: to isolate the image, right click + select Open Image in New Tab). Elements like logos, buttons, etc will interfere with our ability to download the image. Do not exceed 20 images per product. | HN6: Your first image will be set as the lead image for this listing, however, is subject to change upon Wayfair review. For each image uploaded, provide the file name with extension (e.g. PART_1.jpeg) or a direct public URL which leads to a single image (tip: to isolate the image, right click + select Open Image in New Tab). Elements like logos, buttons, etc will interfere with our ability to download the image. Do not exceed 20 images per product. | HO6: Your first image will be set as the lead image for this listing, however, is subject to change upon Wayfair review. For each image uploaded, provide the file name with extension (e.g. PART_1.jpeg) or a direct public URL which leads to a single image (tip: to isolate the image, right click + select Open Image in New Tab). Elements like logos, buttons, etc will interfere with our ability to download the image. Do not exceed 20 images per product. | HP6: Your first image will be set as the lead image for this listing, however, is subject to change upon Wayfair review. For each image uploaded, provide the file name with extension (e.g. PART_1.jpeg) or a direct public URL which leads to a single image (tip: to isolate the image, right click + select Open Image in New Tab). Elements like logos, buttons, etc will interfere with our ability to download the image. Do not exceed 20 images per product. | HQ6: Your first image will be set as the lead image for this listing, however, is subject to change upon Wayfair review. For each image uploaded, provide the file name with extension (e.g. PART_1.jpeg) or a direct public URL which leads to a single image (tip: to isolate the image, right click + select Open Image in New Tab). Elements like logos, buttons, etc will interfere with our ability to download the image. Do not exceed 20 images per product. | HR6: Your first image will be set as the lead image for this listing, however, is subject to change upon Wayfair review. For each image uploaded, provide the file name with extension (e.g. PART_1.jpeg) or a direct public URL which leads to a single image (tip: to isolate the image, right click + select Open Image in New Tab). Elements like logos, buttons, etc will interfere with our ability to download the image. Do not exceed 20 images per product. | HS6: Your first image will be set as the lead image for this listing, however, is subject to change upon Wayfair review. For each image uploaded, provide the file name with extension (e.g. PART_1.jpeg) or a direct public URL which leads to a single image (tip: to isolate the image, right click + select Open Image in New Tab). Elements like logos, buttons, etc will interfere with our ability to download the image. Do not exceed 20 images per product. | HT6: Your first image will be set as the lead image for this listing, however, is subject to change upon Wayfair review. For each image uploaded, provide the file name with extension (e.g. PART_1.jpeg) or a direct public URL which leads to a single image (tip: to isolate the image, right click + select Open Image in New Tab). Elements like logos, buttons, etc will interfere with our ability to download the image. Do not exceed 20 images per product. | HU6: Your first image will be set as the lead image for this listing, however, is subject to change upon Wayfair review. For each image uploaded, provide the file name with extension (e.g. PART_1.jpeg) or a direct public URL which leads to a single image (tip: to isolate the image, right click + select Open Image in New Tab). Elements like logos, buttons, etc will interfere with our ability to download the image. Do not exceed 20 images per product. | HV6: Your first image will be set as the lead image for this listing, however, is subject to change upon Wayfair review. For each image uploaded, provide the file name with extension (e.g. PART_1.jpeg) or a direct public URL which leads to a single image (tip: to isolate the image, right click + select Open Image in New Tab). Elements like logos, buttons, etc will interfere with our ability to download the image. Do not exceed 20 images per product. | HW6: Your first image will be set as the lead image for this listing, however, is subject to change upon Wayfair review. For each image uploaded, provide the file name with extension (e.g. PART_1.jpeg) or a direct public URL which leads to a single image (tip: to isolate the image, right click + select Open Image in New Tab). Elements like logos, buttons, etc will interfere with our ability to download the image. Do not exceed 20 images per product. | HX6: Your first image will be set as the lead image for this listing, however, is subject to change upon Wayfair review. For each image uploaded, provide the file name with extension (e.g. PART_1.jpeg) or a direct public URL which leads to a single image (tip: to isolate the image, right click + select Open Image in New Tab). Elements like logos, buttons, etc will interfere with our ability to download the image. Do not exceed 20 images per product. | HY6: Your first image will be set as the lead image for this listing, however, is subject to change upon Wayfair review. For each image uploaded, provide the file name with extension (e.g. PART_1.jpeg) or a direct public URL which leads to a single image (tip: to isolate the image, right click + select Open Image in New Tab). Elements like logos, buttons, etc will interfere with our ability to download the image. Do not exceed 20 images per product. | HZ6: Your first image will be set as the lead image for this listing, however, is subject to change upon Wayfair review. For each image uploaded, provide the file name with extension (e.g. PART_1.jpeg) or a direct public URL which leads to a single image (tip: to isolate the image, right click + select Open Image in New Tab). Elements like logos, buttons, etc will interfere with our ability to download the image. Do not exceed 20 images per product. | IA6: Your first image will be set as the lead image for this listing, however, is subject to change upon Wayfair review. For each image uploaded, provide the file name with extension (e.g. PART_1.jpeg) or a direct public URL which leads to a single image (tip: to isolate the image, right click + select Open Image in New Tab). Elements like logos, buttons, etc will interfere with our ability to download the image. Do not exceed 20 images per product. | IB6: Your first image will be set as the lead image for this listing, however, is subject to change upon Wayfair review. For each image uploaded, provide the file name with extension (e.g. PART_1.jpeg) or a direct public URL which leads to a single image (tip: to isolate the image, right click + select Open Image in New Tab). Elements like logos, buttons, etc will interfere with our ability to download the image. Do not exceed 20 images per product. | IC6: Your first image will be set as the lead image for this listing, however, is subject to change upon Wayfair review. For each image uploaded, provide the file name with extension (e.g. PART_1.jpeg) or a direct public URL which leads to a single image (tip: to isolate the image, right click + select Open Image in New Tab). Elements like logos, buttons, etc will interfere with our ability to download the image. Do not exceed 20 images per product. | ID6: Your first image will be set as the lead image for this listing, however, is subject to change upon Wayfair review. For each image uploaded, provide the file name with extension (e.g. PART_1.jpeg) or a direct public URL which leads to a single image (tip: to isolate the image, right click + select Open Image in New Tab). Elements like logos, buttons, etc will interfere with our ability to download the image. Do not exceed 20 images per product. | IE6: Your first image will be set as the lead image for this listing, however, is subject to change upon Wayfair review. For each image uploaded, provide the file name with extension (e.g. PART_1.jpeg) or a direct public URL which leads to a single image (tip: to isolate the image, right click + select Open Image in New Tab). Elements like logos, buttons, etc will interfere with our ability to download the image. Do not exceed 20 images per product. | IF6: Your first image will be set as the lead image for this listing, however, is subject to change upon Wayfair review. For each image uploaded, provide the file name with extension (e.g. PART_1.jpeg) or a direct public URL which leads to a single image (tip: to isolate the image, right click + select Open Image in New Tab). Elements like logos, buttons, etc will interfere with our ability to download the image. Do not exceed 20 images per product. | IG6: Your first image will be set as the lead image for this listing, however, is subject to change upon Wayfair review. For each image uploaded, provide the file name with extension (e.g. PART_1.jpeg) or a direct public URL which leads to a single image (tip: to isolate the image, right click + select Open Image in New Tab). Elements like logos, buttons, etc will interfere with our ability to download the image. Do not exceed 20 images per product. | IH6: Your first image will be set as the lead image for this listing, however, is subject to change upon Wayfair review. For each image uploaded, provide the file name with extension (e.g. PART_1.jpeg) or a direct public URL which leads to a single image (tip: to isolate the image, right click + select Open Image in New Tab). Elements like logos, buttons, etc will interfere with our ability to download the image. Do not exceed 20 images per product. | II6: Provide the video’s file name with extension for separate uploads or a direct public URL. Do not exceed 10 videos per product. | IJ6: Provide the video’s file name with extension for separate uploads or a direct public URL. Do not exceed 10 videos per product. | IK6: Provide the document’s file name with extension for separate uploads or a direct public URL. Do not exceed 10 documents per product. | IL6: Select one or more values from the provided list that best describe the document’s purpose. This classification helps customers easily find information like “Installation & Assembly” guides, “Warranty Information,” or “Specifications. | IM6: If the document serves as a legal notice or certification (e.g., “ASTM F2057 - 19,” “ANSI A117.1 Compliant”), select the specific type(s) from the provided list. This is used for compliance and to display certifications to customers. | IN6: Select the country or region where this document is legally applicable. This is crucial for compliance-related documents that may differ across locations. | IO6: Provide the document’s file name with extension for separate uploads or a direct public URL. Do not exceed 10 documents per product. | IP6: Select one or more values from the provided list that best describe the document’s purpose. This classification helps customers easily find information like “Installation & Assembly” guides, “Warranty Information,” or “Specifications. | IQ6: If the document serves as a legal notice or certification (e.g., “ASTM F2057 - 19,” “ANSI A117.1 Compliant”), select the specific type(s) from the provided list. This is used for compliance and to display certifications to customers. | IR6: Select the country or region where this document is legally applicable. This is crucial for compliance-related documents that may differ across locations. | IS6: Provide the document’s file name with extension for separate uploads or a direct public URL. Do not exceed 10 documents per product. | IT6: Select one or more values from the provided list that best describe the document’s purpose. This classification helps customers easily find information like “Installation & Assembly” guides, “Warranty Information,” or “Specifications. | IU6: If the document serves as a legal notice or certification (e.g., “ASTM F2057 - 19,” “ANSI A117.1 Compliant”), select the specific type(s) from the provided list. This is used for compliance and to display certifications to customers. | IV6: Select the country or region where this document is legally applicable. This is crucial for compliance-related documents that may differ across locations. | IW6: Provide the document’s file name with extension for separate uploads or a direct public URL. Do not exceed 10 documents per product. | IX6: Select one or more values from the provided list that best describe the document’s purpose. This classification helps customers easily find information like “Installation & Assembly” guides, “Warranty Information,” or “Specifications. | IY6: If the document serves as a legal notice or certification (e.g., “ASTM F2057 - 19,” “ANSI A117.1 Compliant”), select the specific type(s) from the provided list. This is used for compliance and to display certifications to customers. | IZ6: Select the country or region where this document is legally applicable. This is crucial for compliance-related documents that may differ across locations. | JA6: Provide the document’s file name with extension for separate uploads or a direct public URL. Do not exceed 10 documents per product. | JB6: Select one or more values from the provided list that best describe the document’s purpose. This classification helps customers easily find information like “Installation & Assembly” guides, “Warranty Information,” or “Specifications. | JC6: If the document serves as a legal notice or certification (e.g., “ASTM F2057 - 19,” “ANSI A117.1 Compliant”), select the specific type(s) from the provided list. This is used for compliance and to display certifications to customers. | JD6: Select the country or region where this document is legally applicable. This is crucial for compliance-related documents that may differ across locations. | JE6: Provide the document’s file name with extension for separate uploads or a direct public URL. Do not exceed 10 documents per product. | JF6: Select one or more values from the provided list that best describe the document’s purpose. This classification helps customers easily find information like “Installation & Assembly” guides, “Warranty Information,” or “Specifications. | JG6: If the document serves as a legal notice or certification (e.g., “ASTM F2057 - 19,” “ANSI A117.1 Compliant”), select the specific type(s) from the provided list. This is used for compliance and to display certifications to customers. | JH6: Select the country or region where this document is legally applicable. This is crucial for compliance-related documents that may differ across locations. | JI6: Provide the document’s file name with extension for separate uploads or a direct public URL. Do not exceed 10 documents per product. | JJ6: Select one or more values from the provided list that best describe the document’s purpose. This classification helps customers easily find information like “Installation & Assembly” guides, “Warranty Information,” or “Specifications. | JK6: If the document serves as a legal notice or certification (e.g., “ASTM F2057 - 19,” “ANSI A117.1 Compliant”), select the specific type(s) from the provided list. This is used for compliance and to display certifications to customers. | JL6: Select the country or region where this document is legally applicable. This is crucial for compliance-related documents that may differ across locations. | JM6: Provide the document’s file name with extension for separate uploads or a direct public URL. Do not exceed 10 documents per product. | JN6: Select one or more values from the provided list that best describe the document’s purpose. This classification helps customers easily find information like “Installation & Assembly” guides, “Warranty Information,” or “Specifications. | JO6: If the document serves as a legal notice or certification (e.g., “ASTM F2057 - 19,” “ANSI A117.1 Compliant”), select the specific type(s) from the provided list. This is used for compliance and to display certifications to customers. | JP6: Select the country or region where this document is legally applicable. This is crucial for compliance-related documents that may differ across locations. | JQ6: Provide the document’s file name with extension for separate uploads or a direct public URL. Do not exceed 10 documents per product. | JR6: Select one or more values from the provided list that best describe the document’s purpose. This classification helps customers easily find information like “Installation & Assembly” guides, “Warranty Information,” or “Specifications. | JS6: If the document serves as a legal notice or certification (e.g., “ASTM F2057 - 19,” “ANSI A117.1 Compliant”), select the specific type(s) from the provided list. This is used for compliance and to display certifications to customers. | JT6: Select the country or region where this document is legally applicable. This is crucial for compliance-related documents that may differ across locations. | JU6: Provide the document’s file name with extension for separate uploads or a direct public URL. Do not exceed 10 documents per product. | JV6: Select one or more values from the provided list that best describe the document’s purpose. This classification helps customers easily find information like “Installation & Assembly” guides, “Warranty Information,” or “Specifications. | JW6: If the document serves as a legal notice or certification (e.g., “ASTM F2057 - 19,” “ANSI A117.1 Compliant”), select the specific type(s) from the provided list. This is used for compliance and to display certifications to customers. | JX6: Select the country or region where this document is legally applicable. This is crucial for compliance-related documents that may differ across locations. | JY6: What type of product is this? | JZ6: What is the subject of this product? Please select the most applicable option. If this product does not fit any of the listed options, please enter the correct value. If the product fits into multiple subjects, please tag each subject that applies. Do not tag sub - subjects: e.g. themes that are being shown within the main subject, which could be an image of a city with a billboard. Everything on that billboard should not be tagged for subject. | KA6: What type of surface does this product have? Please enter the most applicable option. If this product does not fit any of the listed options, please enter the correct information. Multiple options can be selected. | KB6: What material is the product made of? | KC6: What type(s) of surfaces is this product compatible with? | KD6: Is the product monogrammed, or does the product feature a customer inputted text? | KE6: Is this product designed for a specific room? Enter more than one option if applicable. | KF6: What is the particular Holiday / Occasion theme or design of the product? Please select one Holiday / Occasion based on option definitions. If no Holiday or Occasion is applicable to the product, please select "No Holiday" | KG6: Does this product and/or packaging have additional advertising or labeling details regarding claims about the product’s origin? Please use this field to provide a qualified or unqualified claim regarding the product origin in accordance with US Federal Trade Commission (FTC) and Canada Competition Bureau regulations. Additionally, if applicable, please use this field to communicate any appropriate qualified, comparative, or descriptive claims regarding the origin of the product. Examples include, but are not limited to, communicating relevant percentage of domestic and non-domestic content (ex: 60% U.S. Content), communicating the origin of certain components of the product (ex: "Hand carved in U.S. — Wood from Philippines"), or communicating where the product was assembled (Ex : “Assembled In Mexico”). See https://www.ftc.gov/tips-advice/business-center/guidance/complying-made-usa-standard#qualified and https://www.competitionbureau.gc.ca/eic/site/cb-bc.nsf/eng/03169.html | KH6: Does this product contain 0% BPA (Bisphenol A), a plastic compound with toxic properties? | KI6: If this is a licensed product, which licensing category does this product fall under? If this product is not an officially-licensed product associated with an active licensing agreement, please mark this as Does Not Apply. | KJ6: Which of the following durability features are applicable to this product? Please select all applicable options from the list. If none apply, please select "No Durability Features." | KK6: Select all features that allow a user to intentionally change the product’s physical dimensions, orientation, or configuration. This includes any design elements meant to be moved, rotated, folded, or expanded (Reclining backrests, height-adjustable legs, etc.) to adapt the product to a specific person or space. | KL6: What is the color of the product? If your color name is not listed, please type in the value. | KM6: What is the total number of pieces included with this product? Count the number of pieces including removable/separate parts that come with the product. (Ex: A sku of storage bins with lids that is a set size of 3 has 6 total # of pieces included- 3 bins & 3 lids). If sku only has bins and no other pieces where set size is 4 then the total # of pieces included is 4. | KN6: What pieces are included with this product? | KO6: What movie / show does this product display? Please only fill out this information if an image of the movie / show is shown on the product. If the move or show is not listed, please enter it manually. | KP6: Select all features that describe the product’s intrinsic performance, certifications, or functional classification rather than its physical parts. This includes invisible treatments and overarching capabilities (Pet Friendly, Disposable, Breathable, etc.) where the benefit is inherent to the product as a whole. | KQ6: For what age group(s) is the product intended or can be safely used by? Please select all that apply. | KR6: [Inches] What is the overall height of the product from top to bottom? Please enter just the number (e.g. 45.5). | KS6: [Inches] What is overall width of the product from side to side? Please enter just the number (e.g. 45.5). | KT6: [Pounds] What is the total weight of this product once assembled? If this product includes multiples of the same item, add weight of one individual unit (e.g. 1 Dining Chair in a set of 2). Please enter just the number (i.e. 45.5). | KU6: Does the manufacturer warranty cover the use of this product in a commercial environment? | KV6: How long does the manufacturer warranty apply for the product used in a commercial (non-residential) environment? If the correct value is not found, please select the closest available answer that is shorter than the warranty length. If warranty length varies by part, please select the answer that matches the part of the product with the shortest warranty. Please use the “Warranty Details” tag for any additional details. | KW6: Please only select "Yes" if you are a part of Wayfair's Compliance Vetting Program and / or your product has been tested and certified to Baby Safety Alliance (BSA) protocols (fka JPMA) for the relevant product category. Wayfair will verify this information. Incorrectly selecting that you are a part of either program may result in your products becoming unfindable until all compliance data is updated and provided. | KX6: Does your product comply with the Uniform Packaging and Labeling Regulations, which requires product packaging to be accurate and provide adequate information as to the identity and quantity of its contents, as well as the name and address of the manufacturer and/or distributor? | KY6: Is this product legally or operationally restricted from being offered for sale to Canadian customers on Wayfair.ca or delivered to Canadian addresses? Select “Yes” only if the product cannot legally be sold or shipped to Canada. For example, if it requires a license or certification you do not hold, or if you operate through a separate Canadian entity that cannot support the listing. | KZ6: Is the packaging for this SKU ISTA Certified (1A, 3A, 6A)? | LA6: Do you have any certifications or credentials related to environmental sustainability, social responsibility, or ethical sourcing (e.g.,OEKO-TEX®, GREENGUARD, GoodWeave, Fair Trade, FSC, etc.)? To see examples of certificates currently part of our Shop Sustainably program, please visit: https://www.aboutwayfair.com/shop-sustainably. Please upload all related certificates so your products can be merchandised as part of the Shop Sustainably program.
A7: Read-Only | B7: Text | C7: Text | D7: Text | E7: Text | F7: Select | G7: Text | H7: Select | I7: Text | J7: Select | K7: Text | L7: Select | M7: Text | N7: Select | O7: Text | P7: Number | Q7: Number | R7: Number | S7: Number | T7: Text | U7: Text | V7: Text | W7: Text | X7: Text | Y7: Text | Z7: Text | AA7: Text | AB7: Text | AC7: Text | AD7: Whole Number | AE7: Whole Number | AF7: Whole Number | AG7: Number | AH7: Select | AI7: Select | AJ7: Select | AK7: Select | AL7: Text | AM7: Yes or No | AN7: Yes or No | AO7: Number | AP7: Number | AQ7: Number | AR7: Number | AS7: Number | AT7: Number | AU7: Number | AV7: Number | AW7: Number | AX7: Number | AY7: Number | AZ7: Number | BA7: Number | BB7: Number | BC7: Number | BD7: Number | BE7: Number | BF7: Number | BG7: Number | BH7: Number | BI7: Number | BJ7: Number | BK7: Number | BL7: Number | BM7: Number | BN7: Number | BO7: Number | BP7: Number | BQ7: Number | BR7: Number | BS7: Number | BT7: Number | BU7: Number | BV7: Number | BW7: Number | BX7: Number | BY7: Number | BZ7: Number | CA7: Number | CB7: Number | CC7: Number | CD7: Number | CE7: Number | CF7: Number | CG7: Number | CH7: Number | CI7: Number | CJ7: Number | CK7: Number | CL7: Number | CM7: Number | CN7: Number | CO7: Number | CP7: Number | CQ7: Number | CR7: Number | CS7: Number | CT7: Number | CU7: Number | CV7: Number | CW7: Number | CX7: Number | CY7: Number | CZ7: Number | DA7: Number | DB7: Number | DC7: Number | DD7: Number | DE7: Number | DF7: Number | DG7: Number | DH7: Number | DI7: Number | DJ7: Number | DK7: Number | DL7: Number | DM7: Number | DN7: Number | DO7: Number | DP7: Number | DQ7: Number | DR7: Number | DS7: Number | DT7: Number | DU7: Number | DV7: Number | DW7: Number | DX7: Number | DY7: Number | DZ7: Number | EA7: Number | EB7: Number | EC7: Number | ED7: Number | EE7: Number | EF7: Number | EG7: Number | EH7: Number | EI7: Number | EJ7: Number | EK7: Number | EL7: Number | EM7: Number | EN7: Number | EO7: Number | EP7: Number | EQ7: Number | ER7: Number | ES7: Number | ET7: Number | EU7: Number | EV7: Number | EW7: Number | EX7: Number | EY7: Number | EZ7: Number | FA7: Number | FB7: Number | FC7: Number | FD7: Number | FE7: Number | FF7: Number | FG7: Number | FH7: Number | FI7: Number | FJ7: Number | FK7: Number | FL7: Number | FM7: Number | FN7: Number | FO7: Number | FP7: Number | FQ7: Number | FR7: Number | FS7: Number | FT7: Number | FU7: Number | FV7: Number | FW7: Number | FX7: Number | FY7: Number | FZ7: Number | GA7: Number | GB7: Number | GC7: Number | GD7: Number | GE7: Number | GF7: Number | GG7: Number | GH7: Number | GI7: Number | GJ7: Number | GK7: Number | GL7: Number | GM7: Number | GN7: Number | GO7: Number | GP7: Number | GQ7: Number | GR7: Number | GS7: Select | GT7: Yes or No | GU7: Select | GV7: Select | GW7: Select | GX7: Select | GY7: Select | GZ7: Select | HA7: Select | HB7: Select | HC7: Select | HD7: Select | HE7: Text | HF7: Text | HG7: Text | HH7: Text | HI7: Text | HJ7: Text | HK7: Text | HL7: Text | HM7: Text | HN7: Text | HO7: Text | HP7: Text | HQ7: Text | HR7: Text | HS7: Text | HT7: Text | HU7: Text | HV7: Text | HW7: Text | HX7: Text | HY7: Text | HZ7: Text | IA7: Text | IB7: Text | IC7: Text | ID7: Text | IE7: Text | IF7: Text | IG7: Text | IH7: Text | II7: Text | IJ7: Text | IK7: Text | IL7: Please choose one or more from the following, using a semicolon (;) to separate each value: Specifications; Installation & Assembly; Owner Manual; Delivery Information; Warranty Information; Certifications; Disclaimers; Buying Guides; Promotions; Dimensions; Marketing Materials; Energy Guide; Other; Product Information Sheet; Digital Law Label | IM7: Please choose one or more from the following, using a semicolon (;) to separate each value: AAFA Certified; AATCC 116 Grade; AATCC 16.1-2014 Grade; AATCC 16.3-2014 Grade; AATCC 8 Grade; AC Rated; ACT Flammability Guidelines Compliant; AHAM CADR Dust rating; AHAM CADR Pollen rating; AHAM CADR Smoke rating; AHMA Certified; AHMA Compliant; AHRI Certified; ANSI A117.1 Compliant; ANSI A137.1 Compliant; ANSI IT9.2 Compliant; ANSI Z1.5A/CGA 9.1M Certified; ANSI Z124.1.2 Compliant; ANSI Z124.3 Compliant; ANSI Z124.6-97 Compliant; ANSI Z21.11.2-2016 - Gas-Fired Unvented Room Heaters and Gas-Fired Unvented Decorative Room Heaters; ANSI Z21.50-2016/CSA 2.22-2016 - Standard for Vented Decorative Gas Appliances; ANSI Z21.60-2017/CSA 2.26-2017- Standard for Decorative Gas Appliances; ANSI Z21.84-2017 - Standard for Manually Lighted/ Natural Gas/ Decorative Gas Appliances; ANSI Z21.88-2017/CSA 2.33-2017- Standard for Vented Gas Fireplace Heaters; ANSI Z358 Compliant; ANSI/BHMA A156 Certified; ANSI/BIFMA M7.1 Standard Test Method for Determining VOC Emissions; ANSI/BIFMA X5.1 Office Seating; ANSI/BIFMA X5.11 Large Occupant Office Seating; ANSI/BIFMA X5.3 Vertical Files; ANSI/BIFMA X5.4 Lounge & Public Seating; ANSI/BIFMA X5.5 Desk Products; ANSI/BIFMA X5.6 Panel Systems; ANSI/BIFMA X5.9 Storage; ANSI/BIFMA X6.1 Educational Seating; ANSI/BIFMA X7.1 Standard for Formaldehyde & TVOC Emissions; ANSI/ESD S20.20 Certified; ANSI/NISO Z39.48 Compliant; ANSI/SOHO S6.5 Small Office/Home Office; APMA Certified; ASHRAE 62.2 Standard Compliant; ASME A112.18.1 Compliant; ASME A112.18.2 Compliant; ASME A112.19.1 Compliant; ASME A112.19.2 Compliant; ASME A112.19.3 Compliant; ASP:02:01 Certification; ASSE 1001 Certified; ASSE 1006 Certified; ASSE 1016 Certified; ASTM 1821-19; ASTM E1590-07 Compliant; ASTM F1004-19 Certified; ASTM F1148-17 Compliant; ASTM F1148-18 Compliant; ASTM F1148-18 Certified; ASTM F1169 - 13 Compliant; ASTM F1487-17 Compliant; ASTM F1821 - 16 Compliant; ASTM F1912-17 Compliant; ASTM F1917 - 12 Compliant; ASTM F2057 - 14; ASTM F2057 - 17; ASTM F2057 - 19 | IN7: Select | IO7: Text | IP7: Please choose one or more from the following, using a semicolon (;) to separate each value: Specifications; Installation & Assembly; Owner Manual; Delivery Information; Warranty Information; Certifications; Disclaimers; Buying Guides; Promotions; Dimensions; Marketing Materials; Energy Guide; Other; Product Information Sheet; Digital Law Label | IQ7: Please choose one or more from the following, using a semicolon (;) to separate each value: AAFA Certified; AATCC 116 Grade; AATCC 16.1-2014 Grade; AATCC 16.3-2014 Grade; AATCC 8 Grade; AC Rated; ACT Flammability Guidelines Compliant; AHAM CADR Dust rating; AHAM CADR Pollen rating; AHAM CADR Smoke rating; AHMA Certified; AHMA Compliant; AHRI Certified; ANSI A117.1 Compliant; ANSI A137.1 Compliant; ANSI IT9.2 Compliant; ANSI Z1.5A/CGA 9.1M Certified; ANSI Z124.1.2 Compliant; ANSI Z124.3 Compliant; ANSI Z124.6-97 Compliant; ANSI Z21.11.2-2016 - Gas-Fired Unvented Room Heaters and Gas-Fired Unvented Decorative Room Heaters; ANSI Z21.50-2016/CSA 2.22-2016 - Standard for Vented Decorative Gas Appliances; ANSI Z21.60-2017/CSA 2.26-2017- Standard for Decorative Gas Appliances; ANSI Z21.84-2017 - Standard for Manually Lighted/ Natural Gas/ Decorative Gas Appliances; ANSI Z21.88-2017/CSA 2.33-2017- Standard for Vented Gas Fireplace Heaters; ANSI Z358 Compliant; ANSI/BHMA A156 Certified; ANSI/BIFMA M7.1 Standard Test Method for Determining VOC Emissions; ANSI/BIFMA X5.1 Office Seating; ANSI/BIFMA X5.11 Large Occupant Office Seating; ANSI/BIFMA X5.3 Vertical Files; ANSI/BIFMA X5.4 Lounge & Public Seating; ANSI/BIFMA X5.5 Desk Products; ANSI/BIFMA X5.6 Panel Systems; ANSI/BIFMA X5.9 Storage; ANSI/BIFMA X6.1 Educational Seating; ANSI/BIFMA X7.1 Standard for Formaldehyde & TVOC Emissions; ANSI/ESD S20.20 Certified; ANSI/NISO Z39.48 Compliant; ANSI/SOHO S6.5 Small Office/Home Office; APMA Certified; ASHRAE 62.2 Standard Compliant; ASME A112.18.1 Compliant; ASME A112.18.2 Compliant; ASME A112.19.1 Compliant; ASME A112.19.2 Compliant; ASME A112.19.3 Compliant; ASP:02:01 Certification; ASSE 1001 Certified; ASSE 1006 Certified; ASSE 1016 Certified; ASTM 1821-19; ASTM E1590-07 Compliant; ASTM F1004-19 Certified; ASTM F1148-17 Compliant; ASTM F1148-18 Compliant; ASTM F1148-18 Certified; ASTM F1169 - 13 Compliant; ASTM F1487-17 Compliant; ASTM F1821 - 16 Compliant; ASTM F1912-17 Compliant; ASTM F1917 - 12 Compliant; ASTM F2057 - 14; ASTM F2057 - 17; ASTM F2057 - 19 | IR7: Select | IS7: Text | IT7: Please choose one or more from the following, using a semicolon (;) to separate each value: Specifications; Installation & Assembly; Owner Manual; Delivery Information; Warranty Information; Certifications; Disclaimers; Buying Guides; Promotions; Dimensions; Marketing Materials; Energy Guide; Other; Product Information Sheet; Digital Law Label | IU7: Please choose one or more from the following, using a semicolon (;) to separate each value: AAFA Certified; AATCC 116 Grade; AATCC 16.1-2014 Grade; AATCC 16.3-2014 Grade; AATCC 8 Grade; AC Rated; ACT Flammability Guidelines Compliant; AHAM CADR Dust rating; AHAM CADR Pollen rating; AHAM CADR Smoke rating; AHMA Certified; AHMA Compliant; AHRI Certified; ANSI A117.1 Compliant; ANSI A137.1 Compliant; ANSI IT9.2 Compliant; ANSI Z1.5A/CGA 9.1M Certified; ANSI Z124.1.2 Compliant; ANSI Z124.3 Compliant; ANSI Z124.6-97 Compliant; ANSI Z21.11.2-2016 - Gas-Fired Unvented Room Heaters and Gas-Fired Unvented Decorative Room Heaters; ANSI Z21.50-2016/CSA 2.22-2016 - Standard for Vented Decorative Gas Appliances; ANSI Z21.60-2017/CSA 2.26-2017- Standard for Decorative Gas Appliances; ANSI Z21.84-2017 - Standard for Manually Lighted/ Natural Gas/ Decorative Gas Appliances; ANSI Z21.88-2017/CSA 2.33-2017- Standard for Vented Gas Fireplace Heaters; ANSI Z358 Compliant; ANSI/BHMA A156 Certified; ANSI/BIFMA M7.1 Standard Test Method for Determining VOC Emissions; ANSI/BIFMA X5.1 Office Seating; ANSI/BIFMA X5.11 Large Occupant Office Seating; ANSI/BIFMA X5.3 Vertical Files; ANSI/BIFMA X5.4 Lounge & Public Seating; ANSI/BIFMA X5.5 Desk Products; ANSI/BIFMA X5.6 Panel Systems; ANSI/BIFMA X5.9 Storage; ANSI/BIFMA X6.1 Educational Seating; ANSI/BIFMA X7.1 Standard for Formaldehyde & TVOC Emissions; ANSI/ESD S20.20 Certified; ANSI/NISO Z39.48 Compliant; ANSI/SOHO S6.5 Small Office/Home Office; APMA Certified; ASHRAE 62.2 Standard Compliant; ASME A112.18.1 Compliant; ASME A112.18.2 Compliant; ASME A112.19.1 Compliant; ASME A112.19.2 Compliant; ASME A112.19.3 Compliant; ASP:02:01 Certification; ASSE 1001 Certified; ASSE 1006 Certified; ASSE 1016 Certified; ASTM 1821-19; ASTM E1590-07 Compliant; ASTM F1004-19 Certified; ASTM F1148-17 Compliant; ASTM F1148-18 Compliant; ASTM F1148-18 Certified; ASTM F1169 - 13 Compliant; ASTM F1487-17 Compliant; ASTM F1821 - 16 Compliant; ASTM F1912-17 Compliant; ASTM F1917 - 12 Compliant; ASTM F2057 - 14; ASTM F2057 - 17; ASTM F2057 - 19 | IV7: Select | IW7: Text | IX7: Please choose one or more from the following, using a semicolon (;) to separate each value: Specifications; Installation & Assembly; Owner Manual; Delivery Information; Warranty Information; Certifications; Disclaimers; Buying Guides; Promotions; Dimensions; Marketing Materials; Energy Guide; Other; Product Information Sheet; Digital Law Label | IY7: Please choose one or more from the following, using a semicolon (;) to separate each value: AAFA Certified; AATCC 116 Grade; AATCC 16.1-2014 Grade; AATCC 16.3-2014 Grade; AATCC 8 Grade; AC Rated; ACT Flammability Guidelines Compliant; AHAM CADR Dust rating; AHAM CADR Pollen rating; AHAM CADR Smoke rating; AHMA Certified; AHMA Compliant; AHRI Certified; ANSI A117.1 Compliant; ANSI A137.1 Compliant; ANSI IT9.2 Compliant; ANSI Z1.5A/CGA 9.1M Certified; ANSI Z124.1.2 Compliant; ANSI Z124.3 Compliant; ANSI Z124.6-97 Compliant; ANSI Z21.11.2-2016 - Gas-Fired Unvented Room Heaters and Gas-Fired Unvented Decorative Room Heaters; ANSI Z21.50-2016/CSA 2.22-2016 - Standard for Vented Decorative Gas Appliances; ANSI Z21.60-2017/CSA 2.26-2017- Standard for Decorative Gas Appliances; ANSI Z21.84-2017 - Standard for Manually Lighted/ Natural Gas/ Decorative Gas Appliances; ANSI Z21.88-2017/CSA 2.33-2017- Standard for Vented Gas Fireplace Heaters; ANSI Z358 Compliant; ANSI/BHMA A156 Certified; ANSI/BIFMA M7.1 Standard Test Method for Determining VOC Emissions; ANSI/BIFMA X5.1 Office Seating; ANSI/BIFMA X5.11 Large Occupant Office Seating; ANSI/BIFMA X5.3 Vertical Files; ANSI/BIFMA X5.4 Lounge & Public Seating; ANSI/BIFMA X5.5 Desk Products; ANSI/BIFMA X5.6 Panel Systems; ANSI/BIFMA X5.9 Storage; ANSI/BIFMA X6.1 Educational Seating; ANSI/BIFMA X7.1 Standard for Formaldehyde & TVOC Emissions; ANSI/ESD S20.20 Certified; ANSI/NISO Z39.48 Compliant; ANSI/SOHO S6.5 Small Office/Home Office; APMA Certified; ASHRAE 62.2 Standard Compliant; ASME A112.18.1 Compliant; ASME A112.18.2 Compliant; ASME A112.19.1 Compliant; ASME A112.19.2 Compliant; ASME A112.19.3 Compliant; ASP:02:01 Certification; ASSE 1001 Certified; ASSE 1006 Certified; ASSE 1016 Certified; ASTM 1821-19; ASTM E1590-07 Compliant; ASTM F1004-19 Certified; ASTM F1148-17 Compliant; ASTM F1148-18 Compliant; ASTM F1148-18 Certified; ASTM F1169 - 13 Compliant; ASTM F1487-17 Compliant; ASTM F1821 - 16 Compliant; ASTM F1912-17 Compliant; ASTM F1917 - 12 Compliant; ASTM F2057 - 14; ASTM F2057 - 17; ASTM F2057 - 19 | IZ7: Select | JA7: Text | JB7: Please choose one or more from the following, using a semicolon (;) to separate each value: Specifications; Installation & Assembly; Owner Manual; Delivery Information; Warranty Information; Certifications; Disclaimers; Buying Guides; Promotions; Dimensions; Marketing Materials; Energy Guide; Other; Product Information Sheet; Digital Law Label | JC7: Please choose one or more from the following, using a semicolon (;) to separate each value: AAFA Certified; AATCC 116 Grade; AATCC 16.1-2014 Grade; AATCC 16.3-2014 Grade; AATCC 8 Grade; AC Rated; ACT Flammability Guidelines Compliant; AHAM CADR Dust rating; AHAM CADR Pollen rating; AHAM CADR Smoke rating; AHMA Certified; AHMA Compliant; AHRI Certified; ANSI A117.1 Compliant; ANSI A137.1 Compliant; ANSI IT9.2 Compliant; ANSI Z1.5A/CGA 9.1M Certified; ANSI Z124.1.2 Compliant; ANSI Z124.3 Compliant; ANSI Z124.6-97 Compliant; ANSI Z21.11.2-2016 - Gas-Fired Unvented Room Heaters and Gas-Fired Unvented Decorative Room Heaters; ANSI Z21.50-2016/CSA 2.22-2016 - Standard for Vented Decorative Gas Appliances; ANSI Z21.60-2017/CSA 2.26-2017- Standard for Decorative Gas Appliances; ANSI Z21.84-2017 - Standard for Manually Lighted/ Natural Gas/ Decorative Gas Appliances; ANSI Z21.88-2017/CSA 2.33-2017- Standard for Vented Gas Fireplace Heaters; ANSI Z358 Compliant; ANSI/BHMA A156 Certified; ANSI/BIFMA M7.1 Standard Test Method for Determining VOC Emissions; ANSI/BIFMA X5.1 Office Seating; ANSI/BIFMA X5.11 Large Occupant Office Seating; ANSI/BIFMA X5.3 Vertical Files; ANSI/BIFMA X5.4 Lounge & Public Seating; ANSI/BIFMA X5.5 Desk Products; ANSI/BIFMA X5.6 Panel Systems; ANSI/BIFMA X5.9 Storage; ANSI/BIFMA X6.1 Educational Seating; ANSI/BIFMA X7.1 Standard for Formaldehyde & TVOC Emissions; ANSI/ESD S20.20 Certified; ANSI/NISO Z39.48 Compliant; ANSI/SOHO S6.5 Small Office/Home Office; APMA Certified; ASHRAE 62.2 Standard Compliant; ASME A112.18.1 Compliant; ASME A112.18.2 Compliant; ASME A112.19.1 Compliant; ASME A112.19.2 Compliant; ASME A112.19.3 Compliant; ASP:02:01 Certification; ASSE 1001 Certified; ASSE 1006 Certified; ASSE 1016 Certified; ASTM 1821-19; ASTM E1590-07 Compliant; ASTM F1004-19 Certified; ASTM F1148-17 Compliant; ASTM F1148-18 Compliant; ASTM F1148-18 Certified; ASTM F1169 - 13 Compliant; ASTM F1487-17 Compliant; ASTM F1821 - 16 Compliant; ASTM F1912-17 Compliant; ASTM F1917 - 12 Compliant; ASTM F2057 - 14; ASTM F2057 - 17; ASTM F2057 - 19 | JD7: Select | JE7: Text | JF7: Please choose one or more from the following, using a semicolon (;) to separate each value: Specifications; Installation & Assembly; Owner Manual; Delivery Information; Warranty Information; Certifications; Disclaimers; Buying Guides; Promotions; Dimensions; Marketing Materials; Energy Guide; Other; Product Information Sheet; Digital Law Label | JG7: Please choose one or more from the following, using a semicolon (;) to separate each value: AAFA Certified; AATCC 116 Grade; AATCC 16.1-2014 Grade; AATCC 16.3-2014 Grade; AATCC 8 Grade; AC Rated; ACT Flammability Guidelines Compliant; AHAM CADR Dust rating; AHAM CADR Pollen rating; AHAM CADR Smoke rating; AHMA Certified; AHMA Compliant; AHRI Certified; ANSI A117.1 Compliant; ANSI A137.1 Compliant; ANSI IT9.2 Compliant; ANSI Z1.5A/CGA 9.1M Certified; ANSI Z124.1.2 Compliant; ANSI Z124.3 Compliant; ANSI Z124.6-97 Compliant; ANSI Z21.11.2-2016 - Gas-Fired Unvented Room Heaters and Gas-Fired Unvented Decorative Room Heaters; ANSI Z21.50-2016/CSA 2.22-2016 - Standard for Vented Decorative Gas Appliances; ANSI Z21.60-2017/CSA 2.26-2017- Standard for Decorative Gas Appliances; ANSI Z21.84-2017 - Standard for Manually Lighted/ Natural Gas/ Decorative Gas Appliances; ANSI Z21.88-2017/CSA 2.33-2017- Standard for Vented Gas Fireplace Heaters; ANSI Z358 Compliant; ANSI/BHMA A156 Certified; ANSI/BIFMA M7.1 Standard Test Method for Determining VOC Emissions; ANSI/BIFMA X5.1 Office Seating; ANSI/BIFMA X5.11 Large Occupant Office Seating; ANSI/BIFMA X5.3 Vertical Files; ANSI/BIFMA X5.4 Lounge & Public Seating; ANSI/BIFMA X5.5 Desk Products; ANSI/BIFMA X5.6 Panel Systems; ANSI/BIFMA X5.9 Storage; ANSI/BIFMA X6.1 Educational Seating; ANSI/BIFMA X7.1 Standard for Formaldehyde & TVOC Emissions; ANSI/ESD S20.20 Certified; ANSI/NISO Z39.48 Compliant; ANSI/SOHO S6.5 Small Office/Home Office; APMA Certified; ASHRAE 62.2 Standard Compliant; ASME A112.18.1 Compliant; ASME A112.18.2 Compliant; ASME A112.19.1 Compliant; ASME A112.19.2 Compliant; ASME A112.19.3 Compliant; ASP:02:01 Certification; ASSE 1001 Certified; ASSE 1006 Certified; ASSE 1016 Certified; ASTM 1821-19; ASTM E1590-07 Compliant; ASTM F1004-19 Certified; ASTM F1148-17 Compliant; ASTM F1148-18 Compliant; ASTM F1148-18 Certified; ASTM F1169 - 13 Compliant; ASTM F1487-17 Compliant; ASTM F1821 - 16 Compliant; ASTM F1912-17 Compliant; ASTM F1917 - 12 Compliant; ASTM F2057 - 14; ASTM F2057 - 17; ASTM F2057 - 19 | JH7: Select | JI7: Text | JJ7: Please choose one or more from the following, using a semicolon (;) to separate each value: Specifications; Installation & Assembly; Owner Manual; Delivery Information; Warranty Information; Certifications; Disclaimers; Buying Guides; Promotions; Dimensions; Marketing Materials; Energy Guide; Other; Product Information Sheet; Digital Law Label | JK7: Please choose one or more from the following, using a semicolon (;) to separate each value: AAFA Certified; AATCC 116 Grade; AATCC 16.1-2014 Grade; AATCC 16.3-2014 Grade; AATCC 8 Grade; AC Rated; ACT Flammability Guidelines Compliant; AHAM CADR Dust rating; AHAM CADR Pollen rating; AHAM CADR Smoke rating; AHMA Certified; AHMA Compliant; AHRI Certified; ANSI A117.1 Compliant; ANSI A137.1 Compliant; ANSI IT9.2 Compliant; ANSI Z1.5A/CGA 9.1M Certified; ANSI Z124.1.2 Compliant; ANSI Z124.3 Compliant; ANSI Z124.6-97 Compliant; ANSI Z21.11.2-2016 - Gas-Fired Unvented Room Heaters and Gas-Fired Unvented Decorative Room Heaters; ANSI Z21.50-2016/CSA 2.22-2016 - Standard for Vented Decorative Gas Appliances; ANSI Z21.60-2017/CSA 2.26-2017- Standard for Decorative Gas Appliances; ANSI Z21.84-2017 - Standard for Manually Lighted/ Natural Gas/ Decorative Gas Appliances; ANSI Z21.88-2017/CSA 2.33-2017- Standard for Vented Gas Fireplace Heaters; ANSI Z358 Compliant; ANSI/BHMA A156 Certified; ANSI/BIFMA M7.1 Standard Test Method for Determining VOC Emissions; ANSI/BIFMA X5.1 Office Seating; ANSI/BIFMA X5.11 Large Occupant Office Seating; ANSI/BIFMA X5.3 Vertical Files; ANSI/BIFMA X5.4 Lounge & Public Seating; ANSI/BIFMA X5.5 Desk Products; ANSI/BIFMA X5.6 Panel Systems; ANSI/BIFMA X5.9 Storage; ANSI/BIFMA X6.1 Educational Seating; ANSI/BIFMA X7.1 Standard for Formaldehyde & TVOC Emissions; ANSI/ESD S20.20 Certified; ANSI/NISO Z39.48 Compliant; ANSI/SOHO S6.5 Small Office/Home Office; APMA Certified; ASHRAE 62.2 Standard Compliant; ASME A112.18.1 Compliant; ASME A112.18.2 Compliant; ASME A112.19.1 Compliant; ASME A112.19.2 Compliant; ASME A112.19.3 Compliant; ASP:02:01 Certification; ASSE 1001 Certified; ASSE 1006 Certified; ASSE 1016 Certified; ASTM 1821-19; ASTM E1590-07 Compliant; ASTM F1004-19 Certified; ASTM F1148-17 Compliant; ASTM F1148-18 Compliant; ASTM F1148-18 Certified; ASTM F1169 - 13 Compliant; ASTM F1487-17 Compliant; ASTM F1821 - 16 Compliant; ASTM F1912-17 Compliant; ASTM F1917 - 12 Compliant; ASTM F2057 - 14; ASTM F2057 - 17; ASTM F2057 - 19 | JL7: Select | JM7: Text | JN7: Please choose one or more from the following, using a semicolon (;) to separate each value: Specifications; Installation & Assembly; Owner Manual; Delivery Information; Warranty Information; Certifications; Disclaimers; Buying Guides; Promotions; Dimensions; Marketing Materials; Energy Guide; Other; Product Information Sheet; Digital Law Label | JO7: Please choose one or more from the following, using a semicolon (;) to separate each value: AAFA Certified; AATCC 116 Grade; AATCC 16.1-2014 Grade; AATCC 16.3-2014 Grade; AATCC 8 Grade; AC Rated; ACT Flammability Guidelines Compliant; AHAM CADR Dust rating; AHAM CADR Pollen rating; AHAM CADR Smoke rating; AHMA Certified; AHMA Compliant; AHRI Certified; ANSI A117.1 Compliant; ANSI A137.1 Compliant; ANSI IT9.2 Compliant; ANSI Z1.5A/CGA 9.1M Certified; ANSI Z124.1.2 Compliant; ANSI Z124.3 Compliant; ANSI Z124.6-97 Compliant; ANSI Z21.11.2-2016 - Gas-Fired Unvented Room Heaters and Gas-Fired Unvented Decorative Room Heaters; ANSI Z21.50-2016/CSA 2.22-2016 - Standard for Vented Decorative Gas Appliances; ANSI Z21.60-2017/CSA 2.26-2017- Standard for Decorative Gas Appliances; ANSI Z21.84-2017 - Standard for Manually Lighted/ Natural Gas/ Decorative Gas Appliances; ANSI Z21.88-2017/CSA 2.33-2017- Standard for Vented Gas Fireplace Heaters; ANSI Z358 Compliant; ANSI/BHMA A156 Certified; ANSI/BIFMA M7.1 Standard Test Method for Determining VOC Emissions; ANSI/BIFMA X5.1 Office Seating; ANSI/BIFMA X5.11 Large Occupant Office Seating; ANSI/BIFMA X5.3 Vertical Files; ANSI/BIFMA X5.4 Lounge & Public Seating; ANSI/BIFMA X5.5 Desk Products; ANSI/BIFMA X5.6 Panel Systems; ANSI/BIFMA X5.9 Storage; ANSI/BIFMA X6.1 Educational Seating; ANSI/BIFMA X7.1 Standard for Formaldehyde & TVOC Emissions; ANSI/ESD S20.20 Certified; ANSI/NISO Z39.48 Compliant; ANSI/SOHO S6.5 Small Office/Home Office; APMA Certified; ASHRAE 62.2 Standard Compliant; ASME A112.18.1 Compliant; ASME A112.18.2 Compliant; ASME A112.19.1 Compliant; ASME A112.19.2 Compliant; ASME A112.19.3 Compliant; ASP:02:01 Certification; ASSE 1001 Certified; ASSE 1006 Certified; ASSE 1016 Certified; ASTM 1821-19; ASTM E1590-07 Compliant; ASTM F1004-19 Certified; ASTM F1148-17 Compliant; ASTM F1148-18 Compliant; ASTM F1148-18 Certified; ASTM F1169 - 13 Compliant; ASTM F1487-17 Compliant; ASTM F1821 - 16 Compliant; ASTM F1912-17 Compliant; ASTM F1917 - 12 Compliant; ASTM F2057 - 14; ASTM F2057 - 17; ASTM F2057 - 19 | JP7: Select | JQ7: Text | JR7: Please choose one or more from the following, using a semicolon (;) to separate each value: Specifications; Installation & Assembly; Owner Manual; Delivery Information; Warranty Information; Certifications; Disclaimers; Buying Guides; Promotions; Dimensions; Marketing Materials; Energy Guide; Other; Product Information Sheet; Digital Law Label | JS7: Please choose one or more from the following, using a semicolon (;) to separate each value: AAFA Certified; AATCC 116 Grade; AATCC 16.1-2014 Grade; AATCC 16.3-2014 Grade; AATCC 8 Grade; AC Rated; ACT Flammability Guidelines Compliant; AHAM CADR Dust rating; AHAM CADR Pollen rating; AHAM CADR Smoke rating; AHMA Certified; AHMA Compliant; AHRI Certified; ANSI A117.1 Compliant; ANSI A137.1 Compliant; ANSI IT9.2 Compliant; ANSI Z1.5A/CGA 9.1M Certified; ANSI Z124.1.2 Compliant; ANSI Z124.3 Compliant; ANSI Z124.6-97 Compliant; ANSI Z21.11.2-2016 - Gas-Fired Unvented Room Heaters and Gas-Fired Unvented Decorative Room Heaters; ANSI Z21.50-2016/CSA 2.22-2016 - Standard for Vented Decorative Gas Appliances; ANSI Z21.60-2017/CSA 2.26-2017- Standard for Decorative Gas Appliances; ANSI Z21.84-2017 - Standard for Manually Lighted/ Natural Gas/ Decorative Gas Appliances; ANSI Z21.88-2017/CSA 2.33-2017- Standard for Vented Gas Fireplace Heaters; ANSI Z358 Compliant; ANSI/BHMA A156 Certified; ANSI/BIFMA M7.1 Standard Test Method for Determining VOC Emissions; ANSI/BIFMA X5.1 Office Seating; ANSI/BIFMA X5.11 Large Occupant Office Seating; ANSI/BIFMA X5.3 Vertical Files; ANSI/BIFMA X5.4 Lounge & Public Seating; ANSI/BIFMA X5.5 Desk Products; ANSI/BIFMA X5.6 Panel Systems; ANSI/BIFMA X5.9 Storage; ANSI/BIFMA X6.1 Educational Seating; ANSI/BIFMA X7.1 Standard for Formaldehyde & TVOC Emissions; ANSI/ESD S20.20 Certified; ANSI/NISO Z39.48 Compliant; ANSI/SOHO S6.5 Small Office/Home Office; APMA Certified; ASHRAE 62.2 Standard Compliant; ASME A112.18.1 Compliant; ASME A112.18.2 Compliant; ASME A112.19.1 Compliant; ASME A112.19.2 Compliant; ASME A112.19.3 Compliant; ASP:02:01 Certification; ASSE 1001 Certified; ASSE 1006 Certified; ASSE 1016 Certified; ASTM 1821-19; ASTM E1590-07 Compliant; ASTM F1004-19 Certified; ASTM F1148-17 Compliant; ASTM F1148-18 Compliant; ASTM F1148-18 Certified; ASTM F1169 - 13 Compliant; ASTM F1487-17 Compliant; ASTM F1821 - 16 Compliant; ASTM F1912-17 Compliant; ASTM F1917 - 12 Compliant; ASTM F2057 - 14; ASTM F2057 - 17; ASTM F2057 - 19 | JT7: Select | JU7: Text | JV7: Please choose one or more from the following, using a semicolon (;) to separate each value: Specifications; Installation & Assembly; Owner Manual; Delivery Information; Warranty Information; Certifications; Disclaimers; Buying Guides; Promotions; Dimensions; Marketing Materials; Energy Guide; Other; Product Information Sheet; Digital Law Label | JW7: Please choose one or more from the following, using a semicolon (;) to separate each value: AAFA Certified; AATCC 116 Grade; AATCC 16.1-2014 Grade; AATCC 16.3-2014 Grade; AATCC 8 Grade; AC Rated; ACT Flammability Guidelines Compliant; AHAM CADR Dust rating; AHAM CADR Pollen rating; AHAM CADR Smoke rating; AHMA Certified; AHMA Compliant; AHRI Certified; ANSI A117.1 Compliant; ANSI A137.1 Compliant; ANSI IT9.2 Compliant; ANSI Z1.5A/CGA 9.1M Certified; ANSI Z124.1.2 Compliant; ANSI Z124.3 Compliant; ANSI Z124.6-97 Compliant; ANSI Z21.11.2-2016 - Gas-Fired Unvented Room Heaters and Gas-Fired Unvented Decorative Room Heaters; ANSI Z21.50-2016/CSA 2.22-2016 - Standard for Vented Decorative Gas Appliances; ANSI Z21.60-2017/CSA 2.26-2017- Standard for Decorative Gas Appliances; ANSI Z21.84-2017 - Standard for Manually Lighted/ Natural Gas/ Decorative Gas Appliances; ANSI Z21.88-2017/CSA 2.33-2017- Standard for Vented Gas Fireplace Heaters; ANSI Z358 Compliant; ANSI/BHMA A156 Certified; ANSI/BIFMA M7.1 Standard Test Method for Determining VOC Emissions; ANSI/BIFMA X5.1 Office Seating; ANSI/BIFMA X5.11 Large Occupant Office Seating; ANSI/BIFMA X5.3 Vertical Files; ANSI/BIFMA X5.4 Lounge & Public Seating; ANSI/BIFMA X5.5 Desk Products; ANSI/BIFMA X5.6 Panel Systems; ANSI/BIFMA X5.9 Storage; ANSI/BIFMA X6.1 Educational Seating; ANSI/BIFMA X7.1 Standard for Formaldehyde & TVOC Emissions; ANSI/ESD S20.20 Certified; ANSI/NISO Z39.48 Compliant; ANSI/SOHO S6.5 Small Office/Home Office; APMA Certified; ASHRAE 62.2 Standard Compliant; ASME A112.18.1 Compliant; ASME A112.18.2 Compliant; ASME A112.19.1 Compliant; ASME A112.19.2 Compliant; ASME A112.19.3 Compliant; ASP:02:01 Certification; ASSE 1001 Certified; ASSE 1006 Certified; ASSE 1016 Certified; ASTM 1821-19; ASTM E1590-07 Compliant; ASTM F1004-19 Certified; ASTM F1148-17 Compliant; ASTM F1148-18 Compliant; ASTM F1148-18 Certified; ASTM F1169 - 13 Compliant; ASTM F1487-17 Compliant; ASTM F1821 - 16 Compliant; ASTM F1912-17 Compliant; ASTM F1917 - 12 Compliant; ASTM F2057 - 14; ASTM F2057 - 17; ASTM F2057 - 19 | JX7: Select | JY7: Select | JZ7: Please choose one or more from the following, using a semicolon (;) to separate each value: Animals; Astrology & Stars; Scenic & Cityscapes; Food & Beverage; Insects; Patriotic; Entertainment; Plants & Flowers; Religious & Spiritual; Nautical & Beach; Abstract; Sports; People; Geography; Fantasy & Sci-Fi; Landscape & Nature; Text & Numbers; Furniture; Novelty & Humor; STEM; Fashion; Buildings & Architecture; Transportation; Bath & Laundry; History & Language; Cities & Countries; Disney/Pixar; No Subject; Education; Birds; U.S. States & Territories; Unavailable | KA7: Select | KB7: Please choose one or more from the following, using a semicolon (;) to separate each value: Fabric; Vinyl; Canvas; Paper; Plastic; PVC; Polycarbonate (PC); Polyethylene Plastic; Glass; Stainless Steel; Polypropylene; Aluminum; Acrylic; Foam; Cardboard / Paper; Gel; Cardboard; Leather; Ceramic; Copper; Faux Leather; Iron; Leather / Faux Leather; Medium Density Fiberboard (MDF); Nylon; Plastic / Acrylic; Polyester; Polymer; Polyvinyl Chloride (PVC); Polyurethane; Porcelain; Polyurethane (PU); Rubber; Recycled P.E.T; Sponge; Synthetic; Steel; Solid Wood; MDF; Particle Board / Chipboard; Plywood / Laminate Board; Paper / Printed Veneer; Real Wood Veneer | KC7: Please choose one or more from the following, using a semicolon (;) to separate each value: Multi-Surface; Flat Surface; Textured Wall; Brick Wall; Cement Wall; Solid Wood; Glass Wall; Stainless Steel; Existing Tile; Chalkboard; Appliance; Mirror; Wallpaper; Painted Gypsum; Acrylic Panel; Orange Peel Wall; Gypsum Wall; Laminate; Plywood Wall; Drywall; Stucco Wall; Ceramic Tile Wall; Concrete; Stone Wall; Medium Density Fiberboard; Unavailable | KD7: Yes or No | KE7: Please choose one or more from the following, using a semicolon (;) to separate each value: Bathroom; Kitchen; Bedroom; Living Room; Laundry Room; Nursery; Dining Room; Pantry; Home Office; Game Room; Foyer; Playroom; Patio; Closet; Restaurant Dining Room; Basement; Garage/Shop; Commercial Office; Backyard; Mudroom/Deck; School Classroom; Hotel Room; Lobby/Reception; Hallway; Studio; Art School; Commercial Kitchen; Does Not Apply; Unavailable | KF7: Select | KG7: Please choose one or more from the following, using a semicolon (;) to separate each value: Made in USA; Made in USA of Imported Materials; Product of Canada; Made In Canada; Does Not Apply | KH7: Yes or No | KI7: Select | KJ7: Please choose one or more from the following, using a semicolon (;) to separate each value: Mold / Mildew Resistant; Water Resistant; No Durability Features; Fade Resistant; Heat Resistant; Stain Resistant; Tip Resistant; Waterproof; Shatter Resistant; Weather Resistant; Rust Resistant; Anodic Protection; Predator Resistant; Drill Resistant; Condensation Free; Antimicrobial; Pry Resistant; Fray Resistant; Non-Staining | KK7: Please choose one or more from the following, using a semicolon (;) to separate each value: Removable; Retractable; Reversible; Configurable / Modular; Trimmable; Rotating; Lift Assist; Double Sided; Glider; Adjustable; Stackable; No Adjustability Features; Does Not Apply; Unavailable | KL7: Please choose one or more from the following, using a semicolon (;) to separate each value: Blue; Black; Brown; White; Green; Gray; Red; Beige; Yellow; Pink; Orange; Purple; Silver; Gold; Clear; Cream; Ivory; Tan; Teal; Navy | KM7: Whole Number | KN7: Please choose one or more from the following, using a semicolon (;) to separate each value: Handle(s); Paste; Does Not Apply; Unavailable | KO7: Please choose one or more from the following, using a semicolon (;) to separate each value: Justice League (All Characters); Disney Princesses (All Characters); The Avengers (All Characters); Mickey Mouse Clubhouse; Harry Potter; Frozen; Charlie Brown; Dr. Seuss; Disney Fairies (All Characters); Star Wars; Toy Story; The Little Mermaid; The Wizard of Oz; Teenage Mutant Ninja Turtles; Finding Nemo; Spongebob Squarepants; Minions; Cars; Hello Kitty; Angry Birds; Dumbo; The Big Bang Theory; My Little Pony; Thomas The Tank Engine & Friends; Betty Boop; Doc McStuffins; Tom & Jerry; Dragons; Berenstain Bears; The Walking Dead; Winnie the Pooh; Scooby-Doo; Beauty & the Beast; Bubble Guppies; Monsters Inc.; Looney Tunes; Pokemon; The Lion King; Sesame Street; Barbie; Asterix; Dora the Explorer; Star Trek; The Muppets; Transformers; Curious George; The Simpsons; Yogi Bear and Friends; Angelina Ballerina; The Polar Express; Peter Pan; Jake and the Neverland Pirates; Pinocchio; Frankenstein; Sofia the First; Peter Rabbit; Planes; Despicable Me; Alice In Wonderland; A Nightmare On Elm Street; Among Us; Bambi; Baby Shark's Big Show; A Christmas Story; 101 Dalmatians; Avatar; Captain Marvel; DuckTales; The Batman; Fantastic Beasts and Where To Find Them; The Office; Blaze and the Monster Machines; Blue's Clues; Dance Moms; Birds of Prey; Black Panther; E.T.; Demon Slayer: Kimetsu no Yaiba; Daniel Tiger's Neighborhood; Finding Dory; Beetlejuice; Descendants; Doom; DC Super Hero Girls; CoComelon; City Streets; Cruella; Child's Play; Darling In The FRANXX; Encanto; Fortnite; Gravity Falls; Friends; Genshin Impact; Gudetama: An Eggcellent Adventure; Ghostbusters; Friday the 13th; Guardians of the Galaxy; Godzilla; Gremlins; Hawkeye; IT; JoJo Siwa; Hulk; Jujutsu Kaisen; Hocus Pocus; Lego; L.O.L. Surprise; Halo; Lady and the Tramp; Mira: Royal Detective; Iron Man; My Neighbor Totoro; My Hero Academia; Monster Jam; Lilo & Stitch; Naruto; Monopoly; Power Rangers; Step Brothers; Jurassic World; Spirited Away; Spider-Man; Mario Kart; PJ Masks; Space Jam; Squad Goals; | KP7: Please choose one or more from the following, using a semicolon (;) to separate each value: Breathable; Dual Sided; Animated; Double Sided; Non-Wall Damaging; Reusable; Vintage; Window Clinging; No General Features | KQ7: Please choose one or more from the following, using a semicolon (;) to separate each value: Newborn (Birth - 6 months old); Infant (6 - 12 Months); Toddler (1 - 3 Years); Pre-school (3 - 5 Years); Youth (5 - 8 Years); Pre-teen (9 - 12 Years); Teen (13+); Adult (18+); All Ages; Adult; Baby; Kid; Teen; Toddler | KR7: Number | KS7: Number | KT7: Number | KU7: Yes or No | KV7: Select | KW7: Select | KX7: Select | KY7: Yes or No | KZ7: Select | LA7: Yes or No
B8: Default Row: | C8: N/A | D8: N/A | E8: N/A | H8: N/A | I8: N/A | J8: N/A | K8: N/A | L8: N/A | M8: N/A | N8: N/A | O8: N/A | P8: N/A | Q8: N/A | R8: N/A | S8: N/A | HE8: N/A | HF8: N/A | HG8: N/A | HH8: N/A | HI8: N/A | HJ8: N/A | HK8: N/A | HL8: N/A | HM8: N/A | HN8: N/A | HO8: N/A | HP8: N/A | HQ8: N/A | HR8: N/A | HS8: N/A | HT8: N/A | HU8: N/A | HV8: N/A | HW8: N/A | HX8: N/A | HY8: N/A | HZ8: N/A | IA8: N/A | IB8: N/A | IC8: N/A | ID8: N/A | IE8: N/A | IF8: N/A | IG8: N/A | IH8: N/A | II8: N/A | IJ8: N/A | IK8: N/A | IL8: N/A | IM8: N/A | IN8: N/A | IO8: N/A | IP8: N/A | IQ8: N/A | IR8: N/A | IS8: N/A | IT8: N/A | IU8: N/A | IV8: N/A | IW8: N/A | IX8: N/A | IY8: N/A | IZ8: N/A | JA8: N/A | JB8: N/A | JC8: N/A | JD8: N/A | JE8: N/A | JF8: N/A | JG8: N/A | JH8: N/A | JI8: N/A | JJ8: N/A | JK8: N/A | JL8: N/A | JM8: N/A | JN8: N/A | JO8: N/A | JP8: N/A | JQ8: N/A | JR8: N/A | JS8: N/A | JT8: N/A | JU8: N/A | JV8: N/A | JW8: N/A | JX8: N/A
A9: =IF('3757 - Wall Stickers (S)'!B9 = "", "", IF('3757-S-WUO_ERR'!A9 = "", "Validated", HYPERLINK("#" & ADDRESS(ROW('3757-S-WUO_TRK'!A9), '3757-S-WUO_TRK'!A9), _xlfn.TEXTAFTER('3757-S-WUO_ERR'!A9, ":")))) -> 0
A10: =IF('3757 - Wall Stickers (S)'!B10 = "", "", IF('3757-S-WUO_ERR'!A10 = "", "Validated", HYPERLINK("#" & ADDRESS(ROW('3757-S-WUO_TRK'!A10), '3757-S-WUO_TRK'!A10), _xlfn.TEXTAFTER('3757-S-WUO_ERR'!A10, ":")))) -> 0
A11: =IF('3757 - Wall Stickers (S)'!B11 = "", "", IF('3757-S-WUO_ERR'!A11 = "", "Validated", HYPERLINK("#" & ADDRESS(ROW('3757-S-WUO_TRK'!A11), '3757-S-WUO_TRK'!A11), _xlfn.TEXTAFTER('3757-S-WUO_ERR'!A11, ":")))) -> 0
A12: =IF('3757 - Wall Stickers (S)'!B12 = "", "", IF('3757-S-WUO_ERR'!A12 = "", "Validated", HYPERLINK("#" & ADDRESS(ROW('3757-S-WUO_TRK'!A12), '3757-S-WUO_TRK'!A12), _xlfn.TEXTAFTER('3757-S-WUO_ERR'!A12, ":")))) -> 0
A13: =IF('3757 - Wall Stickers (S)'!B13 = "", "", IF('3757-S-WUO_ERR'!A13 = "", "Validated", HYPERLINK("#" & ADDRESS(ROW('3757-S-WUO_TRK'!A13), '3757-S-WUO_TRK'!A13), _xlfn.TEXTAFTER('3757-S-WUO_ERR'!A13, ":")))) -> 0
A14: =IF('3757 - Wall Stickers (S)'!B14 = "", "", IF('3757-S-WUO_ERR'!A14 = "", "Validated", HYPERLINK("#" & ADDRESS(ROW('3757-S-WUO_TRK'!A14), '3757-S-WUO_TRK'!A14), _xlfn.TEXTAFTER('3757-S-WUO_ERR'!A14, ":")))) -> 0
A15: =IF('3757 - Wall Stickers (S)'!B15 = "", "", IF('3757-S-WUO_ERR'!A15 = "", "Validated", HYPERLINK("#" & ADDRESS(ROW('3757-S-WUO_TRK'!A15), '3757-S-WUO_TRK'!A15), _xlfn.TEXTAFTER('3757-S-WUO_ERR'!A15, ":")))) -> 0
A16: =IF('3757 - Wall Stickers (S)'!B16 = "", "", IF('3757-S-WUO_ERR'!A16 = "", "Validated", HYPERLINK("#" & ADDRESS(ROW('3757-S-WUO_TRK'!A16), '3757-S-WUO_TRK'!A16), _xlfn.TEXTAFTER('3757-S-WUO_ERR'!A16, ":")))) -> 0
A17: =IF('3757 - Wall Stickers (S)'!B17 = "", "", IF('3757-S-WUO_ERR'!A17 = "", "Validated", HYPERLINK("#" & ADDRESS(ROW('3757-S-WUO_TRK'!A17), '3757-S-WUO_TRK'!A17), _xlfn.TEXTAFTER('3757-S-WUO_ERR'!A17, ":")))) -> 0
A18: =IF('3757 - Wall Stickers (S)'!B18 = "", "", IF('3757-S-WUO_ERR'!A18 = "", "Validated", HYPERLINK("#" & ADDRESS(ROW('3757-S-WUO_TRK'!A18), '3757-S-WUO_TRK'!A18), _xlfn.TEXTAFTER('3757-S-WUO_ERR'!A18, ":")))) -> 0
A19: =IF('3757 - Wall Stickers (S)'!B19 = "", "", IF('3757-S-WUO_ERR'!A19 = "", "Validated", HYPERLINK("#" & ADDRESS(ROW('3757-S-WUO_TRK'!A19), '3757-S-WUO_TRK'!A19), _xlfn.TEXTAFTER('3757-S-WUO_ERR'!A19, ":")))) -> 0
A20: =IF('3757 - Wall Stickers (S)'!B20 = "", "", IF('3757-S-WUO_ERR'!A20 = "", "Validated", HYPERLINK("#" & ADDRESS(ROW('3757-S-WUO_TRK'!A20), '3757-S-WUO_TRK'!A20), _xlfn.TEXTAFTER('3757-S-WUO_ERR'!A20, ":")))) -> 0
... A508: =IF('3757 - Wall Stickers (S)'!B508 = "", "", IF('3757-S-WUO_ERR'!A508 = "", "Validated", HYPERLINK("#" & ADDRESS(ROW('3757-S-WUO_TRK'!A508), '3757-S-WUO_TRK'!A508), _xlfn.TEXTAFTER('3757-S-WUO_ERR'!A508, ":")))) -> 0

Sheet 3757-S-WUO_ERR
B1: 9000 | C1: 9001 | D1: 9005 | E1: 9006 | F1: 9007 | G1: 9008 | H1: 9009 | I1: 9010 | J1: 9011 | K1: 9012 | L1: 9011 | M1: 9012 | N1: 9011 | O1: 9012 | P1: 9017 | Q1: 9070 | R1: 9018 | S1: 9019 | T1: 9020 | U1: 9021 | V1: 9021 | W1: 9021 | X1: 9021 | Y1: 9021 | Z1: 9021 | AA1: 9021 | AB1: 9021 | AC1: 9004 | AD1: 9026 | AE1: 9027 | AF1: 9028 | AG1: 9029 | AH1: 9030 | AI1: 9031 | AJ1: 9032 | AK1: 9033 | AL1: 9034 | AM1: 9035 | AN1: 9036 | AO1: 9037 | AP1: 9038 | AQ1: 9039 | AR1: 9040 | AS1: 9037 | AT1: 9038 | AU1: 9039 | AV1: 9040 | AW1: 9037 | AX1: 9038 | AY1: 9039 | AZ1: 9040 | BA1: 9037 | BB1: 9038 | BC1: 9039 | BD1: 9040 | BE1: 9037 | BF1: 9038 | BG1: 9039 | BH1: 9040 | BI1: 9037 | BJ1: 9038 | BK1: 9039 | BL1: 9040 | BM1: 9037 | BN1: 9038 | BO1: 9039 | BP1: 9040 | BQ1: 9037 | BR1: 9038 | BS1: 9039 | BT1: 9040 | BU1: 9037 | BV1: 9038 | BW1: 9039 | BX1: 9040 | BY1: 9037 | BZ1: 9038 | CA1: 9039 | CB1: 9040 | CC1: 9037 | CD1: 9038 | CE1: 9039 | CF1: 9040 | CG1: 9037 | CH1: 9038 | CI1: 9039 | CJ1: 9040 | CK1: 9037 | CL1: 9038 | CM1: 9039 | CN1: 9040 | CO1: 9037 | CP1: 9038 | CQ1: 9039 | CR1: 9040 | CS1: 9037 | CT1: 9038 | CU1: 9039 | CV1: 9040 | CW1: 9037 | CX1: 9038 | CY1: 9039 | CZ1: 9040 | DA1: 9037 | DB1: 9038 | DC1: 9039 | DD1: 9040 | DE1: 9037 | DF1: 9038 | DG1: 9039 | DH1: 9040 | DI1: 9037 | DJ1: 9038 | DK1: 9039 | DL1: 9040 | DM1: 9037 | DN1: 9038 | DO1: 9039 | DP1: 9040 | DQ1: 9037 | DR1: 9038 | DS1: 9039 | DT1: 9040 | DU1: 9037 | DV1: 9038 | DW1: 9039 | DX1: 9040 | DY1: 9037 | DZ1: 9038 | EA1: 9039 | EB1: 9040 | EC1: 9037 | ED1: 9038 | EE1: 9039 | EF1: 9040 | EG1: 9037 | EH1: 9038 | EI1: 9039 | EJ1: 9040 | EK1: 9037 | EL1: 9038 | EM1: 9039 | EN1: 9040 | EO1: 9037 | EP1: 9038 | EQ1: 9039 | ER1: 9040 | ES1: 9037 | ET1: 9038 | EU1: 9039 | EV1: 9040 | EW1: 9037 | EX1: 9038 | EY1: 9039 | EZ1: 9040 | FA1: 9037 | FB1: 9038 | FC1: 9039 | FD1: 9040 | FE1: 9037 | FF1: 9038 | FG1: 9039 | FH1: 9040 | FI1: 9037 | FJ1: 9038 | FK1: 9039 | FL1: 9040 | FM1: 9037 | FN1: 9038 | FO1: 9039 | FP1: 9040 | FQ1: 9037 | FR1: 9038 | FS1: 9039 | FT1: 9040 | FU1: 9037 | FV1: 9038 | FW1: 9039 | FX1: 9040 | FY1: 9037 | FZ1: 9038 | GA1: 9039 | GB1: 9040 | GC1: 9037 | GD1: 9038 | GE1: 9039 | GF1: 9040 | GG1: 9037 | GH1: 9038 | GI1: 9039 | GJ1: 9040 | GK1: 9037 | GL1: 9038 | GM1: 9039 | GN1: 9040 | GO1: 9037 | GP1: 9038 | GQ1: 9039 | GR1: 9040 | GS1: 647 | GT1: 9041 | GU1: 9042 | GV1: 9043 | GW1: 9042 | GX1: 9043 | GY1: 9042 | GZ1: 9043 | HA1: 9042 | HB1: 9043 | HC1: 9042 | HD1: 9043 | HE1: 9053 | HF1: 9053 | HG1: 9053 | HH1: 9053 | HI1: 9053 | HJ1: 9053 | HK1: 9053 | HL1: 9053 | HM1: 9053 | HN1: 9053 | HO1: 9053 | HP1: 9053 | HQ1: 9053 | HR1: 9053 | HS1: 9053 | HT1: 9053 | HU1: 9053 | HV1: 9053 | HW1: 9053 | HX1: 9053 | HY1: 9053 | HZ1: 9053 | IA1: 9053 | IB1: 9053 | IC1: 9053 | ID1: 9053 | IE1: 9053 | IF1: 9053 | IG1: 9053 | IH1: 9053 | II1: 9058 | IJ1: 9058 | IK1: 9063 | IL1: 9064 | IM1: 9065 | IN1: 9066 | IO1: 9063 | IP1: 9064 | IQ1: 9065 | IR1: 9066 | IS1: 9063 | IT1: 9064 | IU1: 9065 | IV1: 9066 | IW1: 9063 | IX1: 9064 | IY1: 9065 | IZ1: 9066 | JA1: 9063 | JB1: 9064 | JC1: 9065 | JD1: 9066 | JE1: 9063 | JF1: 9064 | JG1: 9065 | JH1: 9066 | JI1: 9063 | JJ1: 9064 | JK1: 9065 | JL1: 9066 | JM1: 9063 | JN1: 9064 | JO1: 9065 | JP1: 9066 | JQ1: 9063 | JR1: 9064 | JS1: 9065 | JT1: 9066 | JU1: 9063 | JV1: 9064 | JW1: 9065 | JX1: 9066 | JY1: 6109 | JZ1: 1966 | KA1: 1217 | KB1: 2385 | KC1: 3538 | KD1: 2389 | KE1: 1560 | KF1: 137 | KG1: 95 | KH1: 807 | KI1: 1379 | KJ1: 1437 | KK1: 1567 | KL1: 1316 | KM1: 521 | KN1: 6253 | KO1: 1388 | KP1: 8653 | KQ1: 1557 | KR1: 769 | KS1: 770 | KT1: 264 | KU1: 28 | KV1: 135 | KW1: 256 | KX1: 31 | KY1: 117 | KZ1: 8205 | LA1: 8462
J2: 1 | K2: 1 | L2: 2 | M2: 2 | N2: 3 | O2: 3 | U2: 1 | V2: 2 | W2: 3 | X2: 4 | Y2: 5 | Z2: 6 | AA2: 7 | AB2: 8 | AO2: 1 | AP2: 1 | AQ2: 1 | AR2: 1 | AS2: 2 | AT2: 2 | AU2: 2 | AV2: 2 | AW2: 3 | AX2: 3 | AY2: 3 | AZ2: 3 | BA2: 4 | BB2: 4 | BC2: 4 | BD2: 4 | BE2: 5 | BF2: 5 | BG2: 5 | BH2: 5 | BI2: 6 | BJ2: 6 | BK2: 6 | BL2: 6 | BM2: 7 | BN2: 7 | BO2: 7 | BP2: 7 | BQ2: 8 | BR2: 8 | BS2: 8 | BT2: 8 | BU2: 9 | BV2: 9 | BW2: 9 | BX2: 9 | BY2: 10 | BZ2: 10 | CA2: 10 | CB2: 10 | CC2: 11 | CD2: 11 | CE2: 11 | CF2: 11 | CG2: 12 | CH2: 12 | CI2: 12 | CJ2: 12 | CK2: 13 | CL2: 13 | CM2: 13 | CN2: 13 | CO2: 14 | CP2: 14 | CQ2: 14 | CR2: 14 | CS2: 15 | CT2: 15 | CU2: 15 | CV2: 15 | CW2: 16 | CX2: 16 | CY2: 16 | CZ2: 16 | DA2: 17 | DB2: 17 | DC2: 17 | DD2: 17 | DE2: 18 | DF2: 18 | DG2: 18 | DH2: 18 | DI2: 19 | DJ2: 19 | DK2: 19 | DL2: 19 | DM2: 20 | DN2: 20 | DO2: 20 | DP2: 20 | DQ2: 21 | DR2: 21 | DS2: 21 | DT2: 21 | DU2: 22 | DV2: 22 | DW2: 22 | DX2: 22 | DY2: 23 | DZ2: 23 | EA2: 23 | EB2: 23 | EC2: 24 | ED2: 24 | EE2: 24 | EF2: 24 | EG2: 25 | EH2: 25 | EI2: 25 | EJ2: 25 | EK2: 26 | EL2: 26 | EM2: 26 | EN2: 26 | EO2: 27 | EP2: 27 | EQ2: 27 | ER2: 27 | ES2: 28 | ET2: 28 | EU2: 28 | EV2: 28 | EW2: 29 | EX2: 29 | EY2: 29 | EZ2: 29 | FA2: 30 | FB2: 30 | FC2: 30 | FD2: 30 | FE2: 31 | FF2: 31 | FG2: 31 | FH2: 31 | FI2: 32 | FJ2: 32 | FK2: 32 | FL2: 32 | FM2: 33 | FN2: 33 | FO2: 33 | FP2: 33 | FQ2: 34 | FR2: 34 | FS2: 34 | FT2: 34 | FU2: 35 | FV2: 35 | FW2: 35 | FX2: 35 | FY2: 36 | FZ2: 36 | GA2: 36 | GB2: 36 | GC2: 37 | GD2: 37 | GE2: 37 | GF2: 37 | GG2: 38 | GH2: 38 | GI2: 38 | GJ2: 38 | GK2: 39 | GL2: 39 | GM2: 39 | GN2: 39 | GO2: 40 | GP2: 40 | GQ2: 40 | GR2: 40 | GU2: 1 | GV2: 1 | GW2: 2 | GX2: 2 | GY2: 3 | GZ2: 3 | HA2: 4 | HB2: 4 | HC2: 5 | HD2: 5 | HE2: 1 | HF2: 2 | HG2: 3 | HH2: 4 | HI2: 5 | HJ2: 6 | HK2: 7 | HL2: 8 | HM2: 9 | HN2: 10 | HO2: 11 | HP2: 12 | HQ2: 13 | HR2: 14 | HS2: 15 | HT2: 16 | HU2: 17 | HV2: 18 | HW2: 19 | HX2: 20 | HY2: 21 | HZ2: 22 | IA2: 23 | IB2: 24 | IC2: 25 | ID2: 26 | IE2: 27 | IF2: 28 | IG2: 29 | IH2: 30 | II2: 1 | IJ2: 2 | IK2: 1 | IL2: 1 | IM2: 1 | IN2: 1 | IO2: 2 | IP2: 2 | IQ2: 2 | IR2: 2 | IS2: 3 | IT2: 3 | IU2: 3 | IV2: 3 | IW2: 4 | IX2: 4 | IY2: 4 | IZ2: 4 | JA2: 5 | JB2: 5 | JC2: 5 | JD2: 5 | JE2: 6 | JF2: 6 | JG2: 6 | JH2: 6 | JI2: 7 | JJ2: 7 | JK2: 7 | JL2: 7 | JM2: 8 | JN2: 8 | JO2: 8 | JP2: 8 | JQ2: 9 | JR2: 9 | JS2: 9 | JT2: 9 | JU2: 10 | JV2: 10 | JW2: 10 | JX2: 10
B3: Basic Information | F3: Branding | H3: Variant Grouping | P3: Pricing | T3: Marketing Information | AC3: Fulfillment Information | AO3: Carton Details | GS3: Compliance | HE3: Media | JY3: Attributes
B4: Required | C4: Required | D4: Recommended | E4: Required | F4: Required | G4: Conditional | H4: Recommended | I4: Conditional | J4: Conditional | K4: Conditional | L4: Conditional | M4: Conditional | N4: Conditional | O4: Conditional | P4: Required | Q4: Additional | R4: Additional | S4: Additional | T4: Conditional | U4: Conditional | V4: Conditional | W4: Conditional | X4: Conditional | Y4: Conditional | Z4: Conditional | AA4: Conditional | AB4: Conditional | AC4: Additional | AD4: Required | AE4: Required | AF4: Required | AG4: Required | AH4: Required | AI4: Conditional | AJ4: Required | AK4: Required | AL4: Conditional | AM4: Conditional | AN4: Conditional | AO4: Required | AP4: Required | AQ4: Required | AR4: Required | AS4: Conditional | AT4: Conditional | AU4: Conditional | AV4: Conditional | AW4: Conditional | AX4: Conditional | AY4: Conditional | AZ4: Conditional | BA4: Conditional | BB4: Conditional | BC4: Conditional | BD4: Conditional | BE4: Conditional | BF4: Conditional | BG4: Conditional | BH4: Conditional | BI4: Conditional | BJ4: Conditional | BK4: Conditional | BL4: Conditional | BM4: Conditional | BN4: Conditional | BO4: Conditional | BP4: Conditional | BQ4: Conditional | BR4: Conditional | BS4: Conditional | BT4: Conditional | BU4: Conditional | BV4: Conditional | BW4: Conditional | BX4: Conditional | BY4: Conditional | BZ4: Conditional | CA4: Conditional | CB4: Conditional | CC4: Conditional | CD4: Conditional | CE4: Conditional | CF4: Conditional | CG4: Conditional | CH4: Conditional | CI4: Conditional | CJ4: Conditional | CK4: Conditional | CL4: Conditional | CM4: Conditional | CN4: Conditional | CO4: Conditional | CP4: Conditional | CQ4: Conditional | CR4: Conditional | CS4: Conditional | CT4: Conditional | CU4: Conditional | CV4: Conditional | CW4: Conditional | CX4: Conditional | CY4: Conditional | CZ4: Conditional | DA4: Conditional | DB4: Conditional | DC4: Conditional | DD4: Conditional | DE4: Conditional | DF4: Conditional | DG4: Conditional | DH4: Conditional | DI4: Conditional | DJ4: Conditional | DK4: Conditional | DL4: Conditional | DM4: Conditional | DN4: Conditional | DO4: Conditional | DP4: Conditional | DQ4: Conditional | DR4: Conditional | DS4: Conditional | DT4: Conditional | DU4: Conditional | DV4: Conditional | DW4: Conditional | DX4: Conditional | DY4: Conditional | DZ4: Conditional | EA4: Conditional | EB4: Conditional | EC4: Conditional | ED4: Conditional | EE4: Conditional | EF4: Conditional | EG4: Conditional | EH4: Conditional | EI4: Conditional | EJ4: Conditional | EK4: Conditional | EL4: Conditional | EM4: Conditional | EN4: Conditional | EO4: Conditional | EP4: Conditional | EQ4: Conditional | ER4: Conditional | ES4: Conditional | ET4: Conditional | EU4: Conditional | EV4: Conditional | EW4: Conditional | EX4: Conditional | EY4: Conditional | EZ4: Conditional | FA4: Conditional | FB4: Conditional | FC4: Conditional | FD4: Conditional | FE4: Conditional | FF4: Conditional | FG4: Conditional | FH4: Conditional | FI4: Conditional | FJ4: Conditional | FK4: Conditional | FL4: Conditional | FM4: Conditional | FN4: Conditional | FO4: Conditional | FP4: Conditional | FQ4: Conditional | FR4: Conditional | FS4: Conditional | FT4: Conditional | FU4: Conditional | FV4: Conditional | FW4: Conditional | FX4: Conditional | FY4: Conditional | FZ4: Conditional | GA4: Conditional | GB4: Conditional | GC4: Conditional | GD4: Conditional | GE4: Conditional | GF4: Conditional | GG4: Conditional | GH4: Conditional | GI4: Conditional | GJ4: Conditional | GK4: Conditional | GL4: Conditional | GM4: Conditional | GN4: Conditional | GO4: Conditional | GP4: Conditional | GQ4: Conditional | GR4: Conditional | GS4: Required | GT4: Required | GU4: Conditional | GV4: Conditional | GW4: Conditional | GX4: Conditional | GY4: Conditional | GZ4: Conditional | HA4: Conditional | HB4: Conditional | HC4: Conditional | HD4: Conditional | HE4: Required | HF4: Additional | HG4: Additional | HH4: Additional | HI4: Additional | HJ4: Additional | HK4: Additional | HL4: Additional | HM4: Additional | HN4: Additional | HO4: Additional | HP4: Additional | HQ4: Additional | HR4: Additional | HS4: Additional | HT4: Additional | HU4: Additional | HV4: Additional | HW4: Additional | HX4: Additional | HY4: Additional | HZ4: Additional | IA4: Additional | IB4: Additional | IC4: Additional | ID4: Additional | IE4: Additional | IF4: Additional | IG4: Additional | IH4: Additional | II4: Additional | IJ4: Additional | IK4: Conditional | IL4: Additional | IM4: Additional | IN4: Additional | IO4: Conditional | IP4: Additional | IQ4: Additional | IR4: Additional | IS4: Conditional | IT4: Additional | IU4: Additional | IV4: Additional | IW4: Conditional | IX4: Additional | IY4: Additional | IZ4: Additional | JA4: Conditional | JB4: Additional | JC4: Additional | JD4: Additional | JE4: Conditional | JF4: Additional | JG4: Additional | JH4: Additional | JI4: Conditional | JJ4: Additional | JK4: Additional | JL4: Additional | JM4: Conditional | JN4: Additional | JO4: Additional | JP4: Additional | JQ4: Conditional | JR4: Additional | JS4: Additional | JT4: Additional | JU4: Conditional | JV4: Additional | JW4: Additional | JX4: Additional | JY4: Required | JZ4: Recommended | KA4: Required | KB4: Required | KC4: Required | KD4: Recommended | KE4: Recommended | KF4: Recommended | KG4: Additional | KH4: Required | KI4: Recommended | KJ4: Recommended | KK4: Recommended | KL4: Required | KM4: Recommended | KN4: Required | KO4: Conditional | KP4: Recommended | KQ4: Recommended | KR4: Required | KS4: Required | KT4: Required | KU4: Recommended | KV4: Conditional | KW4: Recommended | KX4: Required | KY4: Required | KZ4: Recommended | LA4: Recommended
A5: Errors | B5: Supplier Part Number | C5: Manufacturer Part Number | D5: Universal Product Code | E5: Product Name | F5: Brand | G5: Collection Name | H5: Variant Type | I5: Group Reference ID | J5: Variant Grouping 1 | K5: Variant Attribute Name On Site 1 | L5: Variant Grouping 2 | M5: Variant Attribute Name On Site 2 | N5: Variant Grouping 3 | O5: Variant Attribute Name On Site 3 | P5: Base Cost | Q5: Everyday B2B Discount Rate | R5: Minimum Advertised Price | S5: Manufacturer Suggested Retail Price | T5: Marketing Copy | U5: Feature Bullet 1 | V5: Feature Bullet 2 | W5: Feature Bullet 3 | X5: Feature Bullet 4 | Y5: Feature Bullet 5 | Z5: Feature Bullet 6 | AA5: Feature Bullet 7 | AB5: Feature Bullet 8 | AC5: Amazon Seller SKU | AD5: Minimum Order Quantity | AE5: Force Quantity Multiplier | AF5: Display Set Quantity | AG5: Product Weight | AH5: Ship Type | AI5: Freight Class | AJ5: Lead Time | AK5: Replacement Lead Time | AL5: National Motor Freight Class | AM5: Flat Pack | AN5: Ship Palletized | AO5: Carton Weight 1 | AP5: Carton Height 1 | AQ5: Carton Width 1 | AR5: Carton Depth 1 | AS5: Carton Weight 2 | AT5: Carton Height 2 | AU5: Carton Width 2 | AV5: Carton Depth 2 | AW5: Carton Weight 3 | AX5: Carton Height 3 | AY5: Carton Width 3 | AZ5: Carton Depth 3 | BA5: Carton Weight 4 | BB5: Carton Height 4 | BC5: Carton Width 4 | BD5: Carton Depth 4 | BE5: Carton Weight 5 | BF5: Carton Height 5 | BG5: Carton Width 5 | BH5: Carton Depth 5 | BI5: Carton Weight 6 | BJ5: Carton Height 6 | BK5: Carton Width 6 | BL5: Carton Depth 6 | BM5: Carton Weight 7 | BN5: Carton Height 7 | BO5: Carton Width 7 | BP5: Carton Depth 7 | BQ5: Carton Weight 8 | BR5: Carton Height 8 | BS5: Carton Width 8 | BT5: Carton Depth 8 | BU5: Carton Weight 9 | BV5: Carton Height 9 | BW5: Carton Width 9 | BX5: Carton Depth 9 | BY5: Carton Weight 10 | BZ5: Carton Height 10 | CA5: Carton Width 10 | CB5: Carton Depth 10 | CC5: Carton Weight 11 | CD5: Carton Height 11 | CE5: Carton Width 11 | CF5: Carton Depth 11 | CG5: Carton Weight 12 | CH5: Carton Height 12 | CI5: Carton Width 12 | CJ5: Carton Depth 12 | CK5: Carton Weight 13 | CL5: Carton Height 13 | CM5: Carton Width 13 | CN5: Carton Depth 13 | CO5: Carton Weight 14 | CP5: Carton Height 14 | CQ5: Carton Width 14 | CR5: Carton Depth 14 | CS5: Carton Weight 15 | CT5: Carton Height 15 | CU5: Carton Width 15 | CV5: Carton Depth 15 | CW5: Carton Weight 16 | CX5: Carton Height 16 | CY5: Carton Width 16 | CZ5: Carton Depth 16 | DA5: Carton Weight 17 | DB5: Carton Height 17 | DC5: Carton Width 17 | DD5: Carton Depth 17 | DE5: Carton Weight 18 | DF5: Carton Height 18 | DG5: Carton Width 18 | DH5: Carton Depth 18 | DI5: Carton Weight 19 | DJ5: Carton Height 19 | DK5: Carton Width 19 | DL5: Carton Depth 19 | DM5: Carton Weight 20 | DN5: Carton Height 20 | DO5: Carton Width 20 | DP5: Carton Depth 20 | DQ5: Carton Weight 21 | DR5: Carton Height 21 | DS5: Carton Width 21 | DT5: Carton Depth 21 | DU5: Carton Weight 22 | DV5: Carton Height 22 | DW5: Carton Width 22 | DX5: Carton Depth 22 | DY5: Carton Weight 23 | DZ5: Carton Height 23 | EA5: Carton Width 23 | EB5: Carton Depth 23 | EC5: Carton Weight 24 | ED5: Carton Height 24 | EE5: Carton Width 24 | EF5: Carton Depth 24 | EG5: Carton Weight 25 | EH5: Carton Height 25 | EI5: Carton Width 25 | EJ5: Carton Depth 25 | EK5: Carton Weight 26 | EL5: Carton Height 26 | EM5: Carton Width 26 | EN5: Carton Depth 26 | EO5: Carton Weight 27 | EP5: Carton Height 27 | EQ5: Carton Width 27 | ER5: Carton Depth 27 | ES5: Carton Weight 28 | ET5: Carton Height 28 | EU5: Carton Width 28 | EV5: Carton Depth 28 | EW5: Carton Weight 29 | EX5: Carton Height 29 | EY5: Carton Width 29 | EZ5: Carton Depth 29 | FA5: Carton Weight 30 | FB5: Carton Height 30 | FC5: Carton Width 30 | FD5: Carton Depth 30 | FE5: Carton Weight 31 | FF5: Carton Height 31 | FG5: Carton Width 31 | FH5: Carton Depth 31 | FI5: Carton Weight 32 | FJ5: Carton Height 32 | FK5: Carton Width 32 | FL5: Carton Depth 32 | FM5: Carton Weight 33 | FN5: Carton Height 33 | FO5: Carton Width 33 | FP5: Carton Depth 33 | FQ5: Carton Weight 34 | FR5: Carton Height 34 | FS5: Carton Width 34 | FT5: Carton Depth 34 | FU5: Carton Weight 35 | FV5: Carton Height 35 | FW5: Carton Width 35 | FX5: Carton Depth 35 | FY5: Carton Weight 36 | FZ5: Carton Height 36 | GA5: Carton Width 36 | GB5: Carton Depth 36 | GC5: Carton Weight 37 | GD5: Carton Height 37 | GE5: Carton Width 37 | GF5: Carton Depth 37 | GG5: Carton Weight 38 | GH5: Carton Height 38 | GI5: Carton Width 38 | GJ5: Carton Depth 38 | GK5: Carton Weight 39 | GL5: Carton Height 39 | GM5: Carton Width 39 | GN5: Carton Depth 39 | GO5: Carton Weight 40 | GP5: Carton Height 40 | GQ5: Carton Width 40 | GR5: Carton Depth 40 | GS5: Country of Origin | GT5: Warning Required | GU5: Chemical 1 | GV5: Toxicity 1 | GW5: Chemical 2 | GX5: Toxicity 2 | GY5: Chemical 3 | GZ5: Toxicity 3 | HA5: Chemical 4 | HB5: Toxicity 4 | HC5: Chemical 5 | HD5: Toxicity 5 | HE5: Image File Name or URL 1 | HF5: Image File Name or URL 2 | HG5: Image File Name or URL 3 | HH5: Image File Name or URL 4 | HI5: Image File Name or URL 5 | HJ5: Image File Name or URL 6 | HK5: Image File Name or URL 7 | HL5: Image File Name or URL 8 | HM5: Image File Name or URL 9 | HN5: Image File Name or URL 10 | HO5: Image File Name or URL 11 | HP5: Image File Name or URL 12 | HQ5: Image File Name or URL 13 | HR5: Image File Name or URL 14 | HS5: Image File Name or URL 15 | HT5: Image File Name or URL 16 | HU5: Image File Name or URL 17 | HV5: Image File Name or URL 18 | HW5: Image File Name or URL 19 | HX5: Image File Name or URL 20 | HY5: Image File Name or URL 21 | HZ5: Image File Name or URL 22 | IA5: Image File Name or URL 23 | IB5: Image File Name or URL 24 | IC5: Image File Name or URL 25 | ID5: Image File Name or URL 26 | IE5: Image File Name or URL 27 | IF5: Image File Name or URL 28 | IG5: Image File Name or URL 29 | IH5: Image File Name or URL 30 | II5: Video File Name or URL 1 | IJ5: Video File Name or URL 2 | IK5: Document File Name or URL 1 | IL5: Document Type 1 | IM5: Legal Document Type 1 | IN5: Document Region 1 | IO5: Document File Name or URL 2 | IP5: Document Type 2 | IQ5: Legal Document Type 2 | IR5: Document Region 2 | IS5: Document File Name or URL 3 | IT5: Document Type 3 | IU5: Legal Document Type 3 | IV5: Document Region 3 | IW5: Document File Name or URL 4 | IX5: Document Type 4 | IY5: Legal Document Type 4 | IZ5: Document Region 4 | JA5: Document File Name or URL 5 | JB5: Document Type 5 | JC5: Legal Document Type 5 | JD5: Document Region 5 | JE5: Document File Name or URL 6 | JF5: Document Type 6 | JG5: Legal Document Type 6 | JH5: Document Region 6 | JI5: Document File Name or URL 7 | JJ5: Document Type 7 | JK5: Legal Document Type 7 | JL5: Document Region 7 | JM5: Document File Name or URL 8 | JN5: Document Type 8 | JO5: Legal Document Type 8 | JP5: Document Region 8 | JQ5: Document File Name or URL 9 | JR5: Document Type 9 | JS5: Legal Document Type 9 | JT5: Document Region 9 | JU5: Document File Name or URL 10 | JV5: Document Type 10 | JW5: Legal Document Type 10 | JX5: Document Region 10 | JY5: Product Type | JZ5: Subject | KA5: Surface Type | KB5: Material | KC5: Compatible Surfaces | KD5: Personalization or Monogramming | KE5: Room Use | KF5: Holiday / Occasion | KG5: Country of Origin - Additional Details | KH5: BPA Free | KI5: Licensed Product Category | KJ5: Durability | KK5: Adjustability Features | KL5: Color | KM5: Total Number of Pieces Included | KN5: Pieces Included | KO5: Movie / Show Series Name | KP5: General Features | KQ5: Age Group | KR5: Overall Height - Top to Bottom | KS5: Overall Width - Side to Side | KT5: Overall Product Weight | KU5: Commercial Warranty | KV5: Commercial Warranty Length | KW5: Wayfair Compliance Vetting Program (including Baby Safety Alliance fka JPMA) for this product category | KX5: Uniform Packaging and Labeling Regulations (UPLR) Compliant | KY5: Canada Product Restriction | KZ5: ISTA Certified | LA5: Sustainability & Social Responsibility Certifications (North America Only)
